Workbook

Sheet Tóm tắt profile
A1: Thực hành phát triển bền vững theo từng khía cạnh của các khu nghỉ dưỡng
A2: Khu nghỉ dưỡng | B2: Tóm tắt về minh chứng đã công bố | C2: Năng lượng & Khí hậu | D2: Nước | E2: Chất thải & Nhựa | F2: Thực phẩm & Thu mua | G2: Đa dạng sinh học & Hệ sinh thái | H2: Cộng đồng & Con người | I2: Văn hóa & Di sản | J2: Gắn kết khách hàng | K2: Lưu ý
A3: Six Senses Ninh Van Bay | B3: 8/8 khía cạnh; 5 khía cạnh có dữ liệu định lượng; có nguồn đối chiếu bên ngoài ở biodiversity/community. | C3: Điện mặt trời; 739.782 kWh năm 2025, khoảng 26–28% nhu cầu điện. Chưa thấy KPI cường độ năng lượng công khai. | D3: Tiết kiệm nước trong vận hành; chưa thấy KPI nước/khách hoặc phòng có khách công khai. | E3: Chai thủy tinh tái sử dụng; 156.288 chai nhựa tránh dùng; ủ phân hữu cơ và thu gom rác cộng đồng. | F3: 3 vườn hữu cơ; 13.849 kg nông sản hữu cơ; có định hướng thu mua có trách nhiệm nhưng chưa thấy tỷ lệ địa phương. | G3: Bảo tồn voọc, phục hồi san hô và rừng ngập mặn; GreenViet tham gia theo dõi đa dạng sinh học. | H3: Hỗ trợ giáo dục, nước sạch, đèn năng lượng mặt trời và đào tạo bảo tồn cho nhân viên/cộng đồng. | I3: Earth Lab và Langur Lounge giới thiệu văn hóa địa phương gắn với thiên nhiên và bảo tồn. | J3: Langur Discovery, Nature Hike, Langur Talk, Flora Walk và các hoạt động tìm hiểu thiên nhiên. | K3: Nhiều số liệu là đầu ra; ít KPI chuẩn hóa về năng lượng/nước/chất thải.
A4: InterContinental Danang Sun Peninsula Resort | B4: 8/8 khía cạnh; nhiều thực hành định tính; có Green Globe. | C4: Theo dõi năng lượng và áp dụng biện pháp tiết kiệm; chưa thấy KPI cường độ hiện tại. | D4: Thiết bị tiết kiệm nước, tái sử dụng và xử lý nước thải; có hệ thống quản lý nước trong vận hành. | E4: Chai thủy tinh, phân loại và tái chế; xử lý rác hữu cơ và theo dõi chất thải. | F4: Thu mua địa phương và vật liệu ưu tiên môi trường; tránh các loài dễ tổn thương. | G4: Bảo tồn linh trưởng, cầu cho động vật di chuyển và hỗ trợ sinh cảnh Sơn Trà. | H4: Lao động địa phương, đào tạo nhân viên, hợp tác với trường đào tạo và các hoạt động cộng đồng. | I4: Nghệ thuật, kiến trúc và câu chuyện địa phương được đưa vào thiết kế và trải nghiệm. | J4: Resident naturalist, Nature Expeditions, Ecowalks và Primate Appreciation Month. | K4: Ít KPI định lượng cấp property về cường độ tài nguyên.
A5: Banyan Tree Lang Co | B5: 4/8 khía cạnh có bằng chứng hiện tại trong ma trận, có chứng nhận | C5: Chưa thấy KPI hiện tại riêng cho Banyan Tree Lang Co; một số thông tin môi trường là cấp Laguna Lang Co. | D5: Xử lý nước thải và nguồn nước thay thế ở cấp khu phức hợp; không gán trực tiếp thành KPI riêng của resort. | E5: Đóng chai thủy tinh và ủ phân ở cấp khu phức hợp; chưa có KPI hiện tại riêng của resort. | F5: Chưa thấy KPI hiện tại rõ về tỷ lệ thu mua địa phương hoặc thu mua có trách nhiệm. | G5: Birdwatching và chương trình Signature Birds; bằng chứng hiện tại về KPI sinh thái còn hạn chế. | H5: Đào tạo nghề, hỗ trợ cộng đồng và cơ hội việc làm cho nghệ nhân/người khuyết tật. | I5: Thủ công địa phương và câu chuyện văn hóa được đưa vào sản phẩm và trải nghiệm. | J5: Workshop thủ công, Stay for Good và birdwatching; một số hoạt động kết nối trực tiếp nghệ nhân với khách. | K5: Không gán KPI Laguna integrated resort thành KPI của Banyan Tree property.
A6: Topas Ecolodge | B6: 7/8 khía cạnh; nổi bật về địa gắn kết địa phương | C6: Vận hành tiết kiệm năng lượng và sử dụng nguồn tái tạo; chưa có KPI hiệu suất công khai rõ. | D6: Thu gom nước mưa, tái sử dụng nước xám và xử lý nước thải bằng vùng đất ngập nước nhân tạo. | E6: Loại bỏ nhựa dùng một lần; tái sử dụng chai thủy tinh; đưa chất thải thực phẩm cho hộ dân/nông dân địa phương. | F6: >80% thực phẩm và vật tư nhà hàng mua trực tiếp từ nông trại địa phương. | G6: Làm việc trong cảnh quan Hoàng Liên và có các thực hành bảo vệ môi trường; chưa thấy KPI đa dạng sinh học cụ thể. | H6: >98% nhân viên là người dân tộc thiểu số từ các bản xung quanh; hỗ trợ nghệ nhân và đào tạo nghề. | I6: Nghề thủ công, kiến trúc, ẩm thực và câu chuyện địa phương. | J6: Workshop văn hóa, Green Leaf Initiative và hoạt động bảo vệ cảnh quan có sự tham gia của khách. | K6: Ít KPI hiệu suất chuẩn hóa; ASEAN Green Hotel là ghi nhận, không phải audit KPI.
A7: The Westin Resort & Spa Cam Ranh | B7: 8/8 khía cạnh, một vài KPI được chuẩn hóa | C7: Mục tiêu giảm 10% tác động liên quan năng lượng/nước/chất thải vào cuối 2026; đạt 3% đến cuối 2025; 83,5 kg CO₂e/phòng có khách. | D7: 4.539,37 lít nước/phòng có khách. | E7: Chuyển sang chai thủy tinh, tránh hơn 81.000 chai nhựa; có tái chế tại phòng khách. | F7: Thu mua protein và hải sản có trách nhiệm; chưa công bố tỷ lệ. | G7: Cam kết bảo vệ đa dạng sinh học nhưng chưa có KPI về loài hoặc sinh cảnh. | H7: Gây quỹ Road to Give; 1.000 USD năm 2025 và mục tiêu 2.000 USD năm 2026 cho hỗ trợ cộng đồng/giáo dục. | I7: Vật liệu tự nhiên, mái xanh và thiết kế gợi liên hệ tới làng chài địa phương. | J7: Khuyến khích khách tiết kiệm nước, năng lượng, giảm rác và tham gia đóng góp cộng đồng. | K7: Trạng thái Travelife mới được doanh nghiệp công bố; primary directory chưa được truy xuất trong đợt rà.
A8: Six Senses Con Dao | B8: 8/8 khía cạnh, nhiều dữ liệu định lượng cấp cơ sở | C8: Thông gió tự nhiên, vật liệu tái chế và sử dụng một phần năng lượng mặt trời; chưa có KPI cường độ hiện tại. | D8: Nước thải đã xử lý được tái sử dụng cho vườn và cảnh quan. | E8: 97.656 chai nhựa tránh dùng; 305 kg nhựa chuyển hướng khỏi chôn lấp; 1.763 kg rác bãi biển thu gom. | F8: Vườn hữu cơ khoảng 3.000 m²; 5.641,7 kg rau tươi thu hoạch năm 2025. | G8: Bảo tồn rùa xanh; 3.818 rùa con nở và được thả về biển năm 2025, phối hợp với Vườn quốc gia Côn Đảo. | H8: Water for All với 12 máy lọc nước và 3.879 người hưởng lợi; 84 giờ dạy tiếng Anh cho cộng đồng. | I8: Thiết kế lấy cảm hứng từ làng chài Côn Đảo. | J8: Trải nghiệm thả rùa, Earth Lab, tour phát triển bền vững và hoạt động tại vườn. | K8: Có GSTC/Control Union; phần lớn KPI property vẫn là số liệu doanh nghiệp tự công bố
A9: Mango Bay Phu Quoc | B9: 6/8 khía cạnh; nổi bật về vân hành sinh thái và tích hợp địa phương | C9: Thông gió tự nhiên, nước nóng năng lượng mặt trời, ánh sáng tự nhiên và thiết bị tiết kiệm năng lượng. | D9: Bồn cầu lưu lượng thấp, xử lý nước xám bằng bãi lọc trồng cây và tái sử dụng cho vườn/vườn ươm. | E9: Mua hàng số lượng lớn, tái chế giấy/kính và tái sử dụng chất thải hữu cơ. | F9: >85% hoạt động mua hàng từ nhà cung cấp địa phương. | G9: Phối hợp với Wildlife At Risk và Vườn quốc gia Phú Quốc; khảo sát đa dạng sinh học và phục hồi cây bản địa. | H9: >80% nhân viên địa phương. | I9: Thợ thủ công và vật liệu địa phương/recycled materials gắn với bối cảnh Phú Quốc. | J9: Trải nghiệm địa phương; bằng chứng hiện tại về mức tham gia hoặc tác động lên khách còn hạn chế. | K9: Một số bằng chứng biodiversity mang tính lịch sử; chưa tìm thấy current third-party certification.
A10: Avana Retreat | B10: 6/8 khía cạnh; nổi bật về đa dạng sinh học, cộng đồng và văn hóa | C10: Thực hành giảm tác động trong vận hành; chưa thấy KPI hiện tại rõ về năng lượng. | D10: Thực hành tiết kiệm nước; chưa thấy KPI hiện tại rõ về cường độ nước. | E10: Giảm hoặc loại bỏ nhựa dùng một lần; chưa có số liệu giảm định lượng rõ. | F10: Vườn hữu cơ gắn với hoạt động ẩm thực; chưa có tỷ lệ thu mua địa phương định lượng. | G10: Phục hồi rừng; gần 12.000 cây đến 2025; 151 loài; BioScore tăng 24,6% theo đối tác bên ngoài. | H10: 98% nhân viên địa phương; đội ngũ cảnh quan địa phương và hoạt động với nghệ nhân. | I10: Tri thức và văn hóa Thái, H’Mông, Mường được đưa vào kiến trúc, nghề thủ công và hoạt động trải nghiệm. | J10: Thăm vườn, thu hoạch, nấu ăn và workshop văn hóa/thủ công. | K10: Khoảng trống công khai về energy/water; có chênh lệch 90% và 98% local staff giữa nguồn cũ/mới.
A11: Silk Sense Hoi An River Resort | B11: 8/8 khía cạnh; báo cáo vận hành chi tiết | C11: 2,81 kWh/khách năm 2025; tổng điện giảm 12,4%. | D11: Nước giảm từ 0,71 xuống 0,68 m³/khách giai đoạn 2024–2025. | E11: 1.536 kg rác chôn lấp năm 2025; gần 24 tấn rác hữu cơ xử lý bằng Waste2Green năm 2024; mở rộng loại bỏ nhựa dùng một lần. | F11: Tỷ lệ nhà cung cấp địa phương tăng từ 58% lên 80% năm 2025. | G11: Cây bản địa, mặt nước, không gian xanh và giáo dục đa dạng sinh học; chưa có KPI loài. | H11: 95% nhân viên địa phương; gây quỹ 70 triệu đồng hỗ trợ vùng lũ. | I11: Thủ công, nguyên liệu và hoạt động văn hóa địa phương. | J11: Vườn hữu cơ, lớp nấu ăn và thông tin đa dạng sinh học trong hành trình khách. | K11: Một số số liệu diesel trong report không nhất quán nên đã loại khỏi comparison.
A12: Legacy Mekong | B12: 4/8 khía cạnh; chủ yếu là dữ liệu lịch sử | C12: Hệ thống điện mặt trời 500 kWp là dữ liệu lịch sử; chưa có KPI hiện tại được xác minh. | D12: Chưa tìm thấy KPI hiện tại đủ cụ thể. | E12: Chưa tìm thấy KPI hiện tại đủ cụ thể. | F12: Nguyên liệu địa phương và ẩm thực Mekong; chưa có tỷ lệ thu mua hiện tại. | G12: Bảo tồn cây trưởng thành và cảnh quan xanh; chưa có KPI đa dạng sinh học hiện tại. | H12: Chưa tìm thấy chương trình cộng đồng hiện tại có số liệu đủ cụ thể. | I12: Ẩm thực, vật liệu, thiết kế và trải nghiệm gắn với bản sắc Mekong. | J12: Các trải nghiệm hiện tại có trồng xương rồng, workshop, picnic, ẩm thực và hoạt động gắn với địa phương. | K12: Chưa tìm thấy KPI cụ thể về năng lượng, nước, chất thải, cộng đồng hoặc chứng nhận phát triển bền vững ở cấp cơ sở.

Sheet Trọng tâm triển khai
A1: Trọng tâm triển khai của các khu nghỉ dưỡng
A2: Khu nghỉ dưỡng | B2: Trọng tâm triển khai | C2: Các hoạt động nổi bật
A3: Six Senses Ninh Van Bay | B3: Bảo tồn & phục hồi hệ sinh thái; quản lý tài nguyên; cộng đồng & giáo dục | C3: Có hệ thống năng lượng mặt trời, vườn hữu cơ và quản lý chất thải; đồng thời có bảo tồn voọc, san hô, rừng ngập mặn và nhiều chương trình cộng đồng. Earth Lab kết nối các hoạt động này với khách.
A4: InterContinental Danang Sun Peninsula Resort | B4: Bảo tồn thiên nhiên; giáo dục & trải nghiệm thiên nhiên; quản lý vận hành | C4: Bảo tồn linh trưởng được thể hiện qua cầu cho khỉ, trồng cây, naturalist và các chương trình giáo dục. Chủ đề này còn được đưa vào nhiều hoạt động dành cho khách như Green Hub, Kids activities, yoga và F&B.
A5: Banyan Tree Lang Co | B5: Cộng đồng & hòa nhập; văn hóa địa phương; đa dạng sinh học & trải nghiệm | C5: Hỗ trợ đào tạo và cơ hội việc làm cho cộng đồng; thủ công địa phương; hoạt động với nghệ nhân và người khuyết tật; birdwatching và trải nghiệm văn hóa.
A6: Topas Ecolodge | B6: Cộng đồng địa phương; thu mua địa phương; vận hành tiết kiệm tài nguyên | C6: Lao động địa phương, thu mua từ nông hộ, nghề thủ công và trải nghiệm văn hóa; các biện pháp tiết kiệm tài nguyên và giảm nhựa.
A7: The Westin Resort & Spa Cam Ranh | B7: Đo lường hiệu suất môi trường; giảm tác động tài nguyên; cộng đồng | C7: Có mục tiêu giảm 10% phát thải liên quan đến năng lượng, nước và chất thải đến cuối 2026, đã báo cáo mức giảm 3% đến cuối 2025; đồng thời công bố carbon/water footprint và các hoạt động cộng đồng.
A8: Six Senses Con Dao | B8: Bảo tồn loài gắn với trải nghiệm khách; quản lý tài nguyên & chất thải; cộng đồng & trải nghiệm | C8: Bảo tồn rùa là chương trình rất rõ với Vườn quốc gia Côn Đảo; song song có vườn hữu cơ, giảm nhựa, 2R Station, Water for All, lớp tiếng Anh và các hoạt động để khách tham gia.
A9: Mango Bay Phu Quoc | B9: Vận hành ít tác động; cộng đồng & kinh tế địa phương; bảo tồn thiên nhiên | C9: Thông gió tự nhiên, nước nóng năng lượng mặt trời, xử lý và tái sử dụng nước; giảm chất thải; thu mua và lao động địa phương; hỗ trợ bảo tồn Phú Quốc.
A10: Avana Retreat | B10: Phục hồi hệ sinh thái; cộng đồng địa phương; văn hóa & kiến trúc bản địa | C10: Có chương trình phục hồi rừng, gần 12.000 cây đến 2025 và BioScore tăng 24,6%; 98% nhân viên địa phương và nghệ nhân Thái, H’Mông, Mường tham gia vào kiến trúc, nghề thủ công và trải nghiệm.
A11: Silk Sense Hoi An River Resort | B11: Đo lường hiệu suất vận hành; thu mua địa phương; tích hợp sustainability vào trải nghiệm | C11: Theo dõi điện, nước, chất thải và tỷ lệ nhà cung cấp địa phương; vườn hữu cơ; giảm nhựa; hoạt động văn hóa và giáo dục đa dạng sinh học.
A12: Legacy Mekong | B12: Bản sắc địa phương & trải nghiệm; ẩm thực địa phương; khung quản lý cấp tập đoàn | C12: Ẩm thực Mekong, vật liệu và thiết kế gắn với địa phương, cùng các trải nghiệm liên quan đến đời sống và cảnh quan Mekong.

Sheet Mức độ xác minh dữ kiện
A1: Mức độ xác minh về dữ kiện được công khai
A2: Mã | B2: Ý nghĩa | C2: Cách hiểu | D2: Khu nghỉ dưỡng | E2: Năng lượng & Khí hậu | F2: Nước | G2: Chất thải & Nhựa | H2: Thực phẩm & Thu mua | I2: Đa dạng sinh học & Hệ sinh thái | J2: Cộng đồng & Con người | K2: Văn hóa & Di sản | L2: Gắn kết khách hàng | M2: Quản lý / tích hợp
A3: NB+ĐL | B3: Nguồn bên ngoài + dữ liệu định lượng | C3: Có nguồn bên ngoài xác nhận/đối chiếu và có chỉ số định lượng | D3: Six Senses Ninh Van Bay | E3: ĐL | F3: ĐT | G3: ĐL | H3: ĐL | I3: NB+ĐL | J3: NB+ĐL | K3: ĐT | L3: NB | M3: Có tên trong danh bạ GSTC; Control Union (GSTC-I), chu kỳ 2024–2027. Có thêm ghi nhận HICAP 2024.
A4: NB | B4: Nguồn bên ngoài | C4: Có chứng nhận/đối tác/đánh giá bên ngoài nhưng không có chỉ số định lượng phù hợp ở ô này | D4: InterContinental Danang Sun Peninsula Resort | E4: ĐT | F4: NB | G4: ĐT | H4: ĐT | I4: ĐL | J4: ĐT | K4: ĐT | L4: NB | M4: Green Globe xác nhận chứng nhận công khai; khu nghỉ dưỡng cũng công bố Kế hoạch Quản lý Bền vững 2026–2027.
A5: ĐL | B5: Doanh nghiệp công bố định lượng | C5: Có số liệu/chỉ số do doanh nghiệp tự công bố | D5: Banyan Tree Lang Co | E5: TT | F5: BC | G5: BC | H5: TT | I5: ĐL | J5: ĐT | K5: ĐT | L5: ĐT | M5: Có tên trong danh bạ GSTC; Control Union (GSTC-I), chu kỳ 2025–2028. EarthCheck Gold 2022 chỉ dùng như bối cảnh lịch sử/cấp khu phức hợp.
A6: ĐT | B6: Doanh nghiệp công bố định tính | C6: Có thực hành/tuyên bố nhưng chưa có số liệu cụ thể | D6: Topas Ecolodge | E6: ĐT | F6: ĐT | G6: ĐT | H6: ĐL | I6: TT | J6: ĐL | K6: ĐT | L6: ĐT | M6: Được xác nhận nhận Giải Khách sạn Xanh ASEAN 2026; xem đây là ghi nhận độc lập, không phải kiểm toán chứng nhận toàn bộ chỉ số.
A7: TT | B7: Thiếu minh chứng cụ thể | C7: Chưa tìm thấy bằng chứng ở cấp cơ sở đủ cụ thể trong phạm vi nguồn đã rà | D7: The Westin Resort & Spa Cam Ranh | E7: ĐL | F7: ĐL | G7: ĐL | H7: ĐT | I7: ĐT | J7: ĐL | K7: ĐT | L7: ĐT | M7: Marriott công bố trạng thái Travelife Certified; trong đợt rà soát công khai này chưa truy xuất được hồ sơ gốc từ danh bạ Travelife.
A8: BC | B8: Bối cảnh cấp khu phức hợp | C8: Thông tin thuộc khu nghỉ dưỡng tích hợp/điểm đến, không thể quy hoàn toàn cho cơ sở | D8: Six Senses Con Dao | E8: ĐT | F8: ĐT | G8: ĐL | H8: ĐL | I8: ĐL | J8: ĐL | K8: ĐT | L8: ĐT | M8: Có tên trong danh bạ GSTC; Control Union (GSTC-I), chu kỳ 2024–2027, mã GSTC HACU240332-1.
A9: LS | B9: Dữ liệu lịch sử | C9: Có bằng chứng trong quá khứ nhưng chưa xác nhận là hiện trạng năm 2026 | D9: Mango Bay Phu Quoc | E9: ĐT | F9: ĐT | G9: ĐT | H9: ĐL | I9: LS | J9: ĐL | K9: ĐT | L9: TT | M9: Chưa tìm thấy chứng nhận phát triển bền vững bên thứ ba còn hiệu lực trong các nguồn công khai đã rà.
D10: Avana Retreat | E10: TT | F10: TT | G10: ĐT | H10: ĐT | I10: NB | J10: ĐL | K10: ĐT | L10: ĐT | M10: Có đánh giá đa dạng sinh học/văn hóa sinh học từ Guardians of Earth; đây là đánh giá bên ngoài, không phải chứng nhận phát triển bền vững của khách sạn.
D11: Silk Sense Hoi An River Resort | E11: ĐL | F11: ĐL | G11: ĐL | H11: ĐL | I11: ĐT | J11: ĐL | K11: ĐT | L11: ĐT | M11: Khu nghỉ dưỡng công bố Travelife Gold và có Báo cáo Phát triển Bền vững chi tiết; chưa truy xuất được hồ sơ gốc từ danh bạ Travelife trong đợt rà này.
D12: Legacy Mekong | E12: LS | F12: TT | G12: TT | H12: ĐT | I12: NB | J12: TT | K12: NB | L12: ĐT | M12: Từ cuối năm 2025, khu nghỉ dưỡng thuộc Autograph Collection của Marriott và nằm trong định hướng quản lý phát triển bền vững cấp tập đoàn Serve 360. Tuy nhiên, chưa tìm thấy chứng nhận phát triển bền vững hiện hành hoặc bộ KPI môi trường – xã hội được công bố riêng ở cấp khu nghỉ dưỡng.
A23: Mức độ tiến triển của hoạt động | B23: Core & supporting records
A24: Thực hành | B24: 53
A25: Đầu ra | B25: 44
A26: Tạo ra thay đổi | B26: 10
A27: Cam kết | B27: 1

Sheet Dimensions coverage
A1: Tổng hợp minh chứng theo 8 khía cạnh
A2: Các khía cạnh | B2: Số khu nghỉ dưỡng có bằng chứng hiện tại | C2: Có dữ liệu định lượng | D2: Có nguồn bên ngoài | E2: Chỉ có bằng chứng định tính | F2: Thiếu minh chứng cụ thể | G2: Chỉ có bối cảnh/lịch sử
A3: Năng lượng & Khí hậu | B3: =COUNTIF('Mức độ xác minh dữ kiện'!E$3:E$12,"NB+ĐL")+COUNTIF('Mức độ xác minh dữ kiện'!E$3:E$12,"NB")+COUNTIF('Mức độ xác minh dữ kiện'!E$3:E$12,"ĐL")+COUNTIF('Mức độ xác minh dữ kiện'!E$3:E$12,"ĐT") -> 7 | C3: =COUNTIF('Mức độ xác minh dữ kiện'!E$3:E$12,"NB+ĐL")+COUNTIF('Mức độ xác minh dữ kiện'!E$3:E$12,"ĐL") -> 3 | D3: =COUNTIF('Mức độ xác minh dữ kiện'!E$3:E$12,"NB+ĐL")+COUNTIF('Mức độ xác minh dữ kiện'!E$3:E$12,"NB") -> 0 | E3: =COUNTIF('Mức độ xác minh dữ kiện'!E$3:E$12,"ĐT") -> 4 | F3: =COUNTIF('Mức độ xác minh dữ kiện'!E$3:E$12,"TT") -> 2 | G3: =COUNTIF('Mức độ xác minh dữ kiện'!E$3:E$12,"BC")+COUNTIF('Mức độ xác minh dữ kiện'!E$3:E$12,"LS") -> 1
A4: Nước | B4: =COUNTIF('Mức độ xác minh dữ kiện'!F$3:F$12,"NB+ĐL")+COUNTIF('Mức độ xác minh dữ kiện'!F$3:F$12,"NB")+COUNTIF('Mức độ xác minh dữ kiện'!F$3:F$12,"ĐL")+COUNTIF('Mức độ xác minh dữ kiện'!F$3:F$12,"ĐT") -> 7 | C4: =COUNTIF('Mức độ xác minh dữ kiện'!F$3:F$12,"NB+ĐL")+COUNTIF('Mức độ xác minh dữ kiện'!F$3:F$12,"ĐL") -> 2 | D4: =COUNTIF('Mức độ xác minh dữ kiện'!F$3:F$12,"NB+ĐL")+COUNTIF('Mức độ xác minh dữ kiện'!F$3:F$12,"NB") -> 1 | E4: =COUNTIF('Mức độ xác minh dữ kiện'!F$3:F$12,"ĐT") -> 4 | F4: =COUNTIF('Mức độ xác minh dữ kiện'!F$3:F$12,"TT") -> 2 | G4: =COUNTIF('Mức độ xác minh dữ kiện'!F$3:F$12,"BC")+COUNTIF('Mức độ xác minh dữ kiện'!F$3:F$12,"LS") -> 1
A5: Chất thải & Nhựa | B5: =COUNTIF('Mức độ xác minh dữ kiện'!G$3:G$12,"NB+ĐL")+COUNTIF('Mức độ xác minh dữ kiện'!G$3:G$12,"NB")+COUNTIF('Mức độ xác minh dữ kiện'!G$3:G$12,"ĐL")+COUNTIF('Mức độ xác minh dữ kiện'!G$3:G$12,"ĐT") -> 8 | C5: =COUNTIF('Mức độ xác minh dữ kiện'!G$3:G$12,"NB+ĐL")+COUNTIF('Mức độ xác minh dữ kiện'!G$3:G$12,"ĐL") -> 4 | D5: =COUNTIF('Mức độ xác minh dữ kiện'!G$3:G$12,"NB+ĐL")+COUNTIF('Mức độ xác minh dữ kiện'!G$3:G$12,"NB") -> 0 | E5: =COUNTIF('Mức độ xác minh dữ kiện'!G$3:G$12,"ĐT") -> 4 | F5: =COUNTIF('Mức độ xác minh dữ kiện'!G$3:G$12,"TT") -> 1 | G5: =COUNTIF('Mức độ xác minh dữ kiện'!G$3:G$12,"BC")+COUNTIF('Mức độ xác minh dữ kiện'!G$3:G$12,"LS") -> 1
A6: Thực phẩm & Thu mua | B6: =COUNTIF('Mức độ xác minh dữ kiện'!H$3:H$12,"NB+ĐL")+COUNTIF('Mức độ xác minh dữ kiện'!H$3:H$12,"NB")+COUNTIF('Mức độ xác minh dữ kiện'!H$3:H$12,"ĐL")+COUNTIF('Mức độ xác minh dữ kiện'!H$3:H$12,"ĐT") -> 9 | C6: =COUNTIF('Mức độ xác minh dữ kiện'!H$3:H$12,"NB+ĐL")+COUNTIF('Mức độ xác minh dữ kiện'!H$3:H$12,"ĐL") -> 5 | D6: =COUNTIF('Mức độ xác minh dữ kiện'!H$3:H$12,"NB+ĐL")+COUNTIF('Mức độ xác minh dữ kiện'!H$3:H$12,"NB") -> 0 | E6: =COUNTIF('Mức độ xác minh dữ kiện'!H$3:H$12,"ĐT") -> 4 | F6: =COUNTIF('Mức độ xác minh dữ kiện'!H$3:H$12,"TT") -> 1 | G6: =COUNTIF('Mức độ xác minh dữ kiện'!H$3:H$12,"BC")+COUNTIF('Mức độ xác minh dữ kiện'!H$3:H$12,"LS") -> 0
A7: Đa dạng sinh học & Hệ sinh thái | B7: =COUNTIF('Mức độ xác minh dữ kiện'!I$3:I$12,"NB+ĐL")+COUNTIF('Mức độ xác minh dữ kiện'!I$3:I$12,"NB")+COUNTIF('Mức độ xác minh dữ kiện'!I$3:I$12,"ĐL")+COUNTIF('Mức độ xác minh dữ kiện'!I$3:I$12,"ĐT") -> 8 | C7: =COUNTIF('Mức độ xác minh dữ kiện'!I$3:I$12,"NB+ĐL")+COUNTIF('Mức độ xác minh dữ kiện'!I$3:I$12,"ĐL") -> 4 | D7: =COUNTIF('Mức độ xác minh dữ kiện'!I$3:I$12,"NB+ĐL")+COUNTIF('Mức độ xác minh dữ kiện'!I$3:I$12,"NB") -> 3 | E7: =COUNTIF('Mức độ xác minh dữ kiện'!I$3:I$12,"ĐT") -> 2 | F7: =COUNTIF('Mức độ xác minh dữ kiện'!I$3:I$12,"TT") -> 1 | G7: =COUNTIF('Mức độ xác minh dữ kiện'!I$3:I$12,"BC")+COUNTIF('Mức độ xác minh dữ kiện'!I$3:I$12,"LS") -> 1
A8: Cộng đồng & Con người | B8: =COUNTIF('Mức độ xác minh dữ kiện'!J$3:J$12,"NB+ĐL")+COUNTIF('Mức độ xác minh dữ kiện'!J$3:J$12,"NB")+COUNTIF('Mức độ xác minh dữ kiện'!J$3:J$12,"ĐL")+COUNTIF('Mức độ xác minh dữ kiện'!J$3:J$12,"ĐT") -> 9 | C8: =COUNTIF('Mức độ xác minh dữ kiện'!J$3:J$12,"NB+ĐL")+COUNTIF('Mức độ xác minh dữ kiện'!J$3:J$12,"ĐL") -> 7 | D8: =COUNTIF('Mức độ xác minh dữ kiện'!J$3:J$12,"NB+ĐL")+COUNTIF('Mức độ xác minh dữ kiện'!J$3:J$12,"NB") -> 1 | E8: =COUNTIF('Mức độ xác minh dữ kiện'!J$3:J$12,"ĐT") -> 2 | F8: =COUNTIF('Mức độ xác minh dữ kiện'!J$3:J$12,"TT") -> 1 | G8: =COUNTIF('Mức độ xác minh dữ kiện'!J$3:J$12,"BC")+COUNTIF('Mức độ xác minh dữ kiện'!J$3:J$12,"LS") -> 0
A9: Văn hóa & Di sản | B9: =COUNTIF('Mức độ xác minh dữ kiện'!K$3:K$12,"NB+ĐL")+COUNTIF('Mức độ xác minh dữ kiện'!K$3:K$12,"NB")+COUNTIF('Mức độ xác minh dữ kiện'!K$3:K$12,"ĐL")+COUNTIF('Mức độ xác minh dữ kiện'!K$3:K$12,"ĐT") -> 10 | C9: =COUNTIF('Mức độ xác minh dữ kiện'!K$3:K$12,"NB+ĐL")+COUNTIF('Mức độ xác minh dữ kiện'!K$3:K$12,"ĐL") -> 0 | D9: =COUNTIF('Mức độ xác minh dữ kiện'!K$3:K$12,"NB+ĐL")+COUNTIF('Mức độ xác minh dữ kiện'!K$3:K$12,"NB") -> 1 | E9: =COUNTIF('Mức độ xác minh dữ kiện'!K$3:K$12,"ĐT") -> 9 | F9: =COUNTIF('Mức độ xác minh dữ kiện'!K$3:K$12,"TT") -> 0 | G9: =COUNTIF('Mức độ xác minh dữ kiện'!K$3:K$12,"BC")+COUNTIF('Mức độ xác minh dữ kiện'!K$3:K$12,"LS") -> 0
A10: Gắn kết khách hàng | B10: =COUNTIF('Mức độ xác minh dữ kiện'!L$3:L$12,"NB+ĐL")+COUNTIF('Mức độ xác minh dữ kiện'!L$3:L$12,"NB")+COUNTIF('Mức độ xác minh dữ kiện'!L$3:L$12,"ĐL")+COUNTIF('Mức độ xác minh dữ kiện'!L$3:L$12,"ĐT") -> 9 | C10: =COUNTIF('Mức độ xác minh dữ kiện'!L$3:L$12,"NB+ĐL")+COUNTIF('Mức độ xác minh dữ kiện'!L$3:L$12,"ĐL") -> 0 | D10: =COUNTIF('Mức độ xác minh dữ kiện'!L$3:L$12,"NB+ĐL")+COUNTIF('Mức độ xác minh dữ kiện'!L$3:L$12,"NB") -> 2 | E10: =COUNTIF('Mức độ xác minh dữ kiện'!L$3:L$12,"ĐT") -> 7 | F10: =COUNTIF('Mức độ xác minh dữ kiện'!L$3:L$12,"TT") -> 1 | G10: =COUNTIF('Mức độ xác minh dữ kiện'!L$3:L$12,"BC")+COUNTIF('Mức độ xác minh dữ kiện'!L$3:L$12,"LS") -> 0

Sheet Resort coverage
A1: Tổng hợp minh chứng theo khu nghỉ dưỡng
A2: Khu nghỉ dưỡng | B2: Số khía cạnh có bằng chứng hiện tại | C2: Số khía cạnh có dữ liệu định lượng | D2: Số khía cạnh có nguồn bên ngoài | E2: Số khía cạnh chỉ có định tính | F2: Số khía cạnh thiếu minh chứng | G2: Số khía cạnh chỉ có bối cảnh/lịch sử | H2: Tình trạng quản lý / xác minh | I2: Kết luận
A3: Six Senses Ninh Van Bay | B3: =COUNTIF('Mức độ xác minh dữ kiện'!$E3:$L3,"NB+ĐL")+COUNTIF('Mức độ xác minh dữ kiện'!$E3:$L3,"NB")+COUNTIF('Mức độ xác minh dữ kiện'!$E3:$L3,"ĐL")+COUNTIF('Mức độ xác minh dữ kiện'!$E3:$L3,"ĐT") -> 8 | C3: =COUNTIF('Mức độ xác minh dữ kiện'!$E3:$L3,"NB+ĐL")+COUNTIF('Mức độ xác minh dữ kiện'!$E3:$L3,"ĐL") -> 5 | D3: =COUNTIF('Mức độ xác minh dữ kiện'!$E3:$L3,"NB+ĐL")+COUNTIF('Mức độ xác minh dữ kiện'!$E3:$L3,"NB") -> 3 | E3: =COUNTIF('Mức độ xác minh dữ kiện'!$E3:$L3,"ĐT") -> 2 | F3: =COUNTIF('Mức độ xác minh dữ kiện'!$E3:$L3,"TT") -> 0 | G3: =COUNTIF('Mức độ xác minh dữ kiện'!$E3:$L3,"BC")+COUNTIF('Mức độ xác minh dữ kiện'!$E3:$L3,"LS") -> 0 | H3: Có tên trong danh bạ GSTC; Control Union (GSTC-I), chu kỳ 2024–2027. Có thêm ghi nhận HICAP 2024. | I3: Độ phủ đủ 8 chiều; nổi bật về bằng chứng định lượng và nguồn đối chiếu bên ngoài ở đa dạng sinh học/cộng đồng.
A4: InterContinental Danang Sun Peninsula Resort | B4: =COUNTIF('Mức độ xác minh dữ kiện'!$E4:$L4,"NB+ĐL")+COUNTIF('Mức độ xác minh dữ kiện'!$E4:$L4,"NB")+COUNTIF('Mức độ xác minh dữ kiện'!$E4:$L4,"ĐL")+COUNTIF('Mức độ xác minh dữ kiện'!$E4:$L4,"ĐT") -> 8 | C4: =COUNTIF('Mức độ xác minh dữ kiện'!$E4:$L4,"NB+ĐL")+COUNTIF('Mức độ xác minh dữ kiện'!$E4:$L4,"ĐL") -> 1 | D4: =COUNTIF('Mức độ xác minh dữ kiện'!$E4:$L4,"NB+ĐL")+COUNTIF('Mức độ xác minh dữ kiện'!$E4:$L4,"NB") -> 2 | E4: =COUNTIF('Mức độ xác minh dữ kiện'!$E4:$L4,"ĐT") -> 5 | F4: =COUNTIF('Mức độ xác minh dữ kiện'!$E4:$L4,"TT") -> 0 | G4: =COUNTIF('Mức độ xác minh dữ kiện'!$E4:$L4,"BC")+COUNTIF('Mức độ xác minh dữ kiện'!$E4:$L4,"LS") -> 0 | H4: Green Globe xác nhận chứng nhận công khai; khu nghỉ dưỡng cũng công bố Kế hoạch Quản lý Bền vững 2026–2027. | I4: Độ phủ đủ 8 chiều; nhiều nội dung còn định tính, nhưng có xác minh bên ngoài về quản lý và một số nội dung khách/thiên nhiên.
A5: Banyan Tree Lang Co | B5: =COUNTIF('Mức độ xác minh dữ kiện'!$E5:$L5,"NB+ĐL")+COUNTIF('Mức độ xác minh dữ kiện'!$E5:$L5,"NB")+COUNTIF('Mức độ xác minh dữ kiện'!$E5:$L5,"ĐL")+COUNTIF('Mức độ xác minh dữ kiện'!$E5:$L5,"ĐT") -> 4 | C5: =COUNTIF('Mức độ xác minh dữ kiện'!$E5:$L5,"NB+ĐL")+COUNTIF('Mức độ xác minh dữ kiện'!$E5:$L5,"ĐL") -> 1 | D5: =COUNTIF('Mức độ xác minh dữ kiện'!$E5:$L5,"NB+ĐL")+COUNTIF('Mức độ xác minh dữ kiện'!$E5:$L5,"NB") -> 0 | E5: =COUNTIF('Mức độ xác minh dữ kiện'!$E5:$L5,"ĐT") -> 3 | F5: =COUNTIF('Mức độ xác minh dữ kiện'!$E5:$L5,"TT") -> 2 | G5: =COUNTIF('Mức độ xác minh dữ kiện'!$E5:$L5,"BC")+COUNTIF('Mức độ xác minh dữ kiện'!$E5:$L5,"LS") -> 2 | H5: Có tên trong danh bạ GSTC; Control Union (GSTC-I), chu kỳ 2025–2028. EarthCheck Gold 2022 chỉ dùng như bối cảnh lịch sử/cấp khu phức hợp. | I5: Bằng chứng công khai tập trung hơn vào quản lý, cộng đồng và trải nghiệm; chỉ số vận hành ở cấp cơ sở còn hạn chế.
A6: Topas Ecolodge | B6: =COUNTIF('Mức độ xác minh dữ kiện'!$E6:$L6,"NB+ĐL")+COUNTIF('Mức độ xác minh dữ kiện'!$E6:$L6,"NB")+COUNTIF('Mức độ xác minh dữ kiện'!$E6:$L6,"ĐL")+COUNTIF('Mức độ xác minh dữ kiện'!$E6:$L6,"ĐT") -> 7 | C6: =COUNTIF('Mức độ xác minh dữ kiện'!$E6:$L6,"NB+ĐL")+COUNTIF('Mức độ xác minh dữ kiện'!$E6:$L6,"ĐL") -> 2 | D6: =COUNTIF('Mức độ xác minh dữ kiện'!$E6:$L6,"NB+ĐL")+COUNTIF('Mức độ xác minh dữ kiện'!$E6:$L6,"NB") -> 0 | E6: =COUNTIF('Mức độ xác minh dữ kiện'!$E6:$L6,"ĐT") -> 5 | F6: =COUNTIF('Mức độ xác minh dữ kiện'!$E6:$L6,"TT") -> 1 | G6: =COUNTIF('Mức độ xác minh dữ kiện'!$E6:$L6,"BC")+COUNTIF('Mức độ xác minh dữ kiện'!$E6:$L6,"LS") -> 0 | H6: Được xác nhận nhận Giải Khách sạn Xanh ASEAN 2026; xem đây là ghi nhận độc lập, không phải kiểm toán chứng nhận toàn bộ chỉ số. | I6: Mạnh về cộng đồng, thu mua địa phương và bản sắc địa phương; ít bằng chứng hiện tại về đa dạng sinh học định lượng.
A7: The Westin Resort & Spa Cam Ranh | B7: =COUNTIF('Mức độ xác minh dữ kiện'!$E7:$L7,"NB+ĐL")+COUNTIF('Mức độ xác minh dữ kiện'!$E7:$L7,"NB")+COUNTIF('Mức độ xác minh dữ kiện'!$E7:$L7,"ĐL")+COUNTIF('Mức độ xác minh dữ kiện'!$E7:$L7,"ĐT") -> 8 | C7: =COUNTIF('Mức độ xác minh dữ kiện'!$E7:$L7,"NB+ĐL")+COUNTIF('Mức độ xác minh dữ kiện'!$E7:$L7,"ĐL") -> 4 | D7: =COUNTIF('Mức độ xác minh dữ kiện'!$E7:$L7,"NB+ĐL")+COUNTIF('Mức độ xác minh dữ kiện'!$E7:$L7,"NB") -> 0 | E7: =COUNTIF('Mức độ xác minh dữ kiện'!$E7:$L7,"ĐT") -> 4 | F7: =COUNTIF('Mức độ xác minh dữ kiện'!$E7:$L7,"TT") -> 0 | G7: =COUNTIF('Mức độ xác minh dữ kiện'!$E7:$L7,"BC")+COUNTIF('Mức độ xác minh dữ kiện'!$E7:$L7,"LS") -> 0 | H7: Marriott công bố trạng thái Travelife Certified; trong đợt rà soát công khai này chưa truy xuất được hồ sơ gốc từ danh bạ Travelife. | I7: Có độ phủ đủ 8 chiều và một số chỉ số vận hành đã chuẩn hóa; ít nguồn ngoài được truy xuất công khai trong đợt rà.
A8: Six Senses Con Dao | B8: =COUNTIF('Mức độ xác minh dữ kiện'!$E8:$L8,"NB+ĐL")+COUNTIF('Mức độ xác minh dữ kiện'!$E8:$L8,"NB")+COUNTIF('Mức độ xác minh dữ kiện'!$E8:$L8,"ĐL")+COUNTIF('Mức độ xác minh dữ kiện'!$E8:$L8,"ĐT") -> 8 | C8: =COUNTIF('Mức độ xác minh dữ kiện'!$E8:$L8,"NB+ĐL")+COUNTIF('Mức độ xác minh dữ kiện'!$E8:$L8,"ĐL") -> 4 | D8: =COUNTIF('Mức độ xác minh dữ kiện'!$E8:$L8,"NB+ĐL")+COUNTIF('Mức độ xác minh dữ kiện'!$E8:$L8,"NB") -> 0 | E8: =COUNTIF('Mức độ xác minh dữ kiện'!$E8:$L8,"ĐT") -> 4 | F8: =COUNTIF('Mức độ xác minh dữ kiện'!$E8:$L8,"TT") -> 0 | G8: =COUNTIF('Mức độ xác minh dữ kiện'!$E8:$L8,"BC")+COUNTIF('Mức độ xác minh dữ kiện'!$E8:$L8,"LS") -> 0 | H8: Có tên trong danh bạ GSTC; Control Union (GSTC-I), chu kỳ 2024–2027, mã GSTC HACU240332-1. | I8: Độ phủ đủ 8 chiều, nhiều chỉ số định lượng ở cấp cơ sở; có xác minh quản lý qua GSTC.
A9: Mango Bay Phu Quoc | B9: =COUNTIF('Mức độ xác minh dữ kiện'!$E9:$L9,"NB+ĐL")+COUNTIF('Mức độ xác minh dữ kiện'!$E9:$L9,"NB")+COUNTIF('Mức độ xác minh dữ kiện'!$E9:$L9,"ĐL")+COUNTIF('Mức độ xác minh dữ kiện'!$E9:$L9,"ĐT") -> 6 | C9: =COUNTIF('Mức độ xác minh dữ kiện'!$E9:$L9,"NB+ĐL")+COUNTIF('Mức độ xác minh dữ kiện'!$E9:$L9,"ĐL") -> 2 | D9: =COUNTIF('Mức độ xác minh dữ kiện'!$E9:$L9,"NB+ĐL")+COUNTIF('Mức độ xác minh dữ kiện'!$E9:$L9,"NB") -> 0 | E9: =COUNTIF('Mức độ xác minh dữ kiện'!$E9:$L9,"ĐT") -> 4 | F9: =COUNTIF('Mức độ xác minh dữ kiện'!$E9:$L9,"TT") -> 1 | G9: =COUNTIF('Mức độ xác minh dữ kiện'!$E9:$L9,"BC")+COUNTIF('Mức độ xác minh dữ kiện'!$E9:$L9,"LS") -> 1 | H9: Chưa tìm thấy chứng nhận phát triển bền vững bên thứ ba còn hiệu lực trong các nguồn công khai đã rà. | I9: Nổi bật ở thu mua địa phương và cộng đồng; một phần bằng chứng đa dạng sinh học là dữ liệu lịch sử.
A10: Avana Retreat | B10: =COUNTIF('Mức độ xác minh dữ kiện'!$E10:$L10,"NB+ĐL")+COUNTIF('Mức độ xác minh dữ kiện'!$E10:$L10,"NB")+COUNTIF('Mức độ xác minh dữ kiện'!$E10:$L10,"ĐL")+COUNTIF('Mức độ xác minh dữ kiện'!$E10:$L10,"ĐT") -> 6 | C10: =COUNTIF('Mức độ xác minh dữ kiện'!$E10:$L10,"NB+ĐL")+COUNTIF('Mức độ xác minh dữ kiện'!$E10:$L10,"ĐL") -> 1 | D10: =COUNTIF('Mức độ xác minh dữ kiện'!$E10:$L10,"NB+ĐL")+COUNTIF('Mức độ xác minh dữ kiện'!$E10:$L10,"NB") -> 1 | E10: =COUNTIF('Mức độ xác minh dữ kiện'!$E10:$L10,"ĐT") -> 4 | F10: =COUNTIF('Mức độ xác minh dữ kiện'!$E10:$L10,"TT") -> 2 | G10: =COUNTIF('Mức độ xác minh dữ kiện'!$E10:$L10,"BC")+COUNTIF('Mức độ xác minh dữ kiện'!$E10:$L10,"LS") -> 0 | H10: Có đánh giá đa dạng sinh học/văn hóa sinh học từ Guardians of Earth; đây là đánh giá bên ngoài, không phải chứng nhận phát triển bền vững của khách sạn. | I10: Nổi bật ở cộng đồng và đa dạng sinh học; còn khoảng trống công khai ở năng lượng và nước.
A11: Silk Sense Hoi An River Resort | B11: =COUNTIF('Mức độ xác minh dữ kiện'!$E11:$L11,"NB+ĐL")+COUNTIF('Mức độ xác minh dữ kiện'!$E11:$L11,"NB")+COUNTIF('Mức độ xác minh dữ kiện'!$E11:$L11,"ĐL")+COUNTIF('Mức độ xác minh dữ kiện'!$E11:$L11,"ĐT") -> 8 | C11: =COUNTIF('Mức độ xác minh dữ kiện'!$E11:$L11,"NB+ĐL")+COUNTIF('Mức độ xác minh dữ kiện'!$E11:$L11,"ĐL") -> 5 | D11: =COUNTIF('Mức độ xác minh dữ kiện'!$E11:$L11,"NB+ĐL")+COUNTIF('Mức độ xác minh dữ kiện'!$E11:$L11,"NB") -> 0 | E11: =COUNTIF('Mức độ xác minh dữ kiện'!$E11:$L11,"ĐT") -> 3 | F11: =COUNTIF('Mức độ xác minh dữ kiện'!$E11:$L11,"TT") -> 0 | G11: =COUNTIF('Mức độ xác minh dữ kiện'!$E11:$L11,"BC")+COUNTIF('Mức độ xác minh dữ kiện'!$E11:$L11,"LS") -> 0 | H11: Khu nghỉ dưỡng công bố Travelife Gold và có Báo cáo Phát triển Bền vững chi tiết; chưa truy xuất được hồ sơ gốc từ danh bạ Travelife trong đợt rà này. | I11: Độ phủ đủ 8 chiều và nhiều chỉ số vận hành định lượng/chuẩn hóa; nguồn ngoài còn hạn chế trong đợt rà công khai.
A12: Legacy Mekong | B12: =COUNTIF('Mức độ xác minh dữ kiện'!$E12:$L12,"NB+ĐL")+COUNTIF('Mức độ xác minh dữ kiện'!$E12:$L12,"NB")+COUNTIF('Mức độ xác minh dữ kiện'!$E12:$L12,"ĐL")+COUNTIF('Mức độ xác minh dữ kiện'!$E12:$L12,"ĐT") -> 4 | C12: =COUNTIF('Mức độ xác minh dữ kiện'!$E12:$L12,"NB+ĐL")+COUNTIF('Mức độ xác minh dữ kiện'!$E12:$L12,"ĐL") -> 0 | D12: =COUNTIF('Mức độ xác minh dữ kiện'!$E12:$L12,"NB+ĐL")+COUNTIF('Mức độ xác minh dữ kiện'!$E12:$L12,"NB") -> 2 | E12: =COUNTIF('Mức độ xác minh dữ kiện'!$E12:$L12,"ĐT") -> 2 | F12: =COUNTIF('Mức độ xác minh dữ kiện'!$E12:$L12,"TT") -> 3 | G12: =COUNTIF('Mức độ xác minh dữ kiện'!$E12:$L12,"BC")+COUNTIF('Mức độ xác minh dữ kiện'!$E12:$L12,"LS") -> 1 | H12: Từ cuối 2025, khu nghỉ dưỡng thuộc Autograph Collection của Marriott và nằm trong khung phát triển bền vững cấp tập đoàn | I12: Đã có evidence về vài khía cạnh, nhưng dữ liệu định lượng và KPI môi trường, xã hội từ khu nghỉ dưỡng vẫn còn hạn chế

Sheet Kết luận
A1: Tổng hợp minh chứng theo khu nghỉ dưỡng
A2: Kết quả chính | B2: Minh chứng từ bộ dữ liệu | C2: Ý nghĩa phân tích | D2: Cần tránh kết luận
A3: 1. Phạm vi công bố rộng nhưng mức độ minh chứng giữa các khía cạnh rất khác nhau. | B3: Văn hóa & Di sản: 10/10 khu nghỉ dưỡng có thông tin nhưng 0/10 có dữ liệu định lượng. Cộng đồng & Con người: 9/10 có thông tin hiện tại, trong đó 7/10 có dữ liệu định lượng. | C3: Việc một nội dung được đề cập nhiều không có nghĩa nội dung đó đã được đo lường đầy đủ. | D3: Không kết luận Văn hóa & Di sản kém quan trọng chỉ vì thiếu KPI.
A4: 2. Phát triển bền vững trong mẫu không chỉ xoay quanh môi trường; Cộng đồng & Con người là một trong những khía cạnh được đo lường rõ nhất. | B4: Cộng đồng & Con người: 9/10 có bằng chứng hiện tại, 7/10 có dữ liệu định lượng — cao hơn Năng lượng (3/10) và Nước (2/10). | C4: Có thể xem phát triển bền vững trong hospitality qua việc làm, đào tạo, thu mua địa phương và sinh kế, không chỉ qua điện, nước hay nhựa. | D4: Không suy ra tác động xã hội thực tế tốt hơn tác động môi trường chỉ vì có nhiều số liệu hơn.
A5: 3. Hiệu suất môi trường vẫn khó so sánh trực tiếp giữa các khu nghỉ dưỡng. | B5: Năng lượng và Nước đều có bằng chứng hiện tại ở 7/10 khu nghỉ dưỡng; dữ liệu định lượng lần lượt là 3/10 và 2/10. Westin Cam Ranh và Silk Sense có chỉ số cường độ rõ theo đêm phòng/đêm khách. | C5: Dữ liệu công khai chưa đủ đồng nhất để so sánh hiệu quả sử dụng tài nguyên giữa các cơ sở. | D5: Không so sánh trực tiếp kWh, nước hay carbon nếu mẫu số và phạm vi đo khác nhau.
A6: 4. Thông tin công bố vẫn thiên về thực hành và đầu ra hơn là thay đổi thực tế. | B6: Trong 108 mục cốt lõi + bổ trợ: 53 mục ở mức Thực hành, 44 mục ở mức Đầu ra, khoảng 10 mục cho thấy thay đổi và 1 mục là Cam kết. | C6: Các khu nghỉ dưỡng khá rõ về việc đã làm gì và tạo ra bao nhiêu, nhưng ít thông tin hơn về thay đổi dài hạn. | D6: Không coi đầu ra là tác động cuối cùng.
A7: 5. Gắn kết khách hàng khá phổ biến nhưng ít được đo lường ở mức kết quả. | B7: Gắn kết khách hàng có bằng chứng hiện tại ở 9/10 khu nghỉ dưỡng; ma trận chưa có khu nghỉ dưỡng nào đạt nhóm định lượng ở cấp so sánh cho khía cạnh này. | C7: Phát triển bền vững đã đi vào trải nghiệm khách ở nhiều nơi, nhưng công bố chủ yếu cho biết hoạt động tồn tại hoặc số lượt tham gia, ít đo thay đổi nhận thức/hành vi. | D7: Không kết luận khách đã thay đổi hành vi nếu chưa có minh chứng.
A8: 6. Xác minh bên ngoài tập trung nhiều hơn ở chứng nhận/quản lý và một số dự án đa dạng sinh học. | B8: GSTC/Green Globe xác minh ở cấp hệ thống quản lý; đa dạng sinh học có thêm GreenViet, Guardians of Earth… Trong khi nhiều KPI về năng lượng, chất thải và thu mua vẫn do doanh nghiệp tự công bố. | C8: Chứng nhận hệ thống và xác minh từng KPI là hai việc khác nhau. | D8: Không dùng chứng nhận để nói mọi KPI của khu nghỉ dưỡng đều đã được kiểm toán.
A9: 7. Phạm vi công bố và mức độ mạnh của minh chứng là hai khái niệm khác nhau. | B9: InterContinental có thông tin ở 8/8 khía cạnh nhưng chỉ 1 khía cạnh có dữ liệu định lượng; Silk Sense cũng 8/8 nhưng có 5 khía cạnh định lượng. Banyan Tree có chứng nhận mạnh nhưng KPI vận hành ở cấp khu nghỉ dưỡng còn ít. | C9: Không thể đánh giá mức độ minh bạch chỉ bằng số khía cạnh hoặc số mục thông tin. | D9: Không chuyển kết quả thành bảng xếp hạng khu nghỉ dưỡng nào 'bền vững hơn'.

Sheet Dữ liệu thô
A1: Resort | B1: Năm | C1: Dimension | D1: Practice / Initiative | E1: Thông tin / Minh chứng chính | F1: Keep? | G1: Chỉ số | H1: Đơn vị | I1: Loại minh chứng | J1: Guest-facing? | K1: Evidence Stage | L1: Ghi chú | M1: Discussion Tag | N1: Operational Area(s) | O1: Mức độ tích hợp | P1: Nguồn | Q1: Source Link
A2: Six Senses Ninh Van Bay | B2: 2025 | C2: Energy & Climate | D2: Solar energy – Ninh Van Greens | E2: Solar farm tạo khoảng 26–28% điện sử dụng của resort; năm 2025 tạo 739.782 kWh điện tái tạo. | F2: Core | G2: 739782 | H2: kWh | I2: B – Doanh nghiệp công bố định lượng | J2: No – Back-of-house | K2: Output | L2: KPI định lượng rõ, nhưng là số liệu doanh nghiệp tự công bố; chưa cho biết cường độ sử dụng năng lượng hay mức giảm so với mốc cơ sở. | M2: Integration; Evidence & Transparency | N2: Engineering / Sustainability | O2: Tích hợp vào vận hành | P2: Trang chính thức của khu nghỉ dưỡng | Q2: https://www.sixsenses.com/en/hotels-resorts/asia-the-pacific/vietnam/ninh-van-bay/sustainability/
A3: Six Senses Ninh Van Bay | B3: Current review | C3: Energy & Climate | D3: Energy intensity trend | E3: Trong các nguồn đã rà, chưa tìm thấy KPI công khai kiểu kWh/occupied room hoặc kWh/guest night của riêng Ninh Van Bay theo thời gian. | F3: Data gap | I3: E – Chưa tìm thấy minh chứng cụ thể | J3: No – Back-of-house | K3: Data gap | L3: 739.782 kWh là đầu ra của điện mặt trời, không cho biết tổng hiệu quả năng lượng của khu nghỉ dưỡng có cải thiện hay không. | M3: Evidence & Transparency | N3: Engineering / Sustainability | O3: Tích hợp vào vận hành | Q3: https://www.sixsenses.com/en/hotels-resorts/asia-the-pacific/vietnam/ninh-van-bay/sustainability/
A4: Six Senses Ninh Van Bay | B4: Current review | C4: Energy & Climate | D4: Property-level GHG emissions | E4: Có brand-level climate measurement approach, nhưng chưa thấy Scope 1/2 emissions hoặc carbon/occupied room riêng của Ninh Van Bay trong các nguồn đã rà. | F4: Data gap | I4: E – Chưa tìm thấy minh chứng cụ thể | J4: No – Back-of-house | K4: Data gap | L4: Giúp phân biệt quản trị cấp thương hiệu với hiệu suất công bố cấp khu nghỉ dưỡng. | M4: Evidence & Transparency | N4: Management / Engineering / Sustainability | O4: Tích hợp ở hệ thống quản lý | Q4: https://www.sixsenses.com/en/sustainability/impacts/
A5: Six Senses Ninh Van Bay | B5: Current | C5: Water | D5: Water conservation in resort operations | E5: Property mô tả water conservation là một phần của định hướng vận hành bền vững tại resort. | F5: Supporting | I5: C – Doanh nghiệp công bố định tính | J5: No – Back-of-house | K5: Practice | L5: Có mô tả thực hành nhưng chưa có KPI định lượng về lượng nước sử dụng hoặc tiết kiệm. | M5: Breadth; Evidence & Transparency | N5: Engineering / Sustainability | O5: Tích hợp vào vận hành | P5: Trang chính thức của khu nghỉ dưỡng | Q5: https://www.sixsenses.com/en/hotels-resorts/asia-the-pacific/vietnam/ninh-van-bay/sustainability/
A6: Six Senses Ninh Van Bay | B6: Current review | C6: Water | D6: Water-use performance | E6: Chưa tìm thấy water/guest night, water/occupied room hoặc reduction % công khai cho riêng property trong các nguồn đã rà. | F6: Data gap | I6: E – Chưa tìm thấy minh chứng cụ thể | J6: No – Back-of-house | K6: Data gap | L6: Nên giữ để đối chiếu với các khu nghỉ dưỡng có KPI hiệu suất sử dụng nước nếu xuất hiện trong mẫu nghiên cứu. | M6: Evidence & Transparency | N6: Engineering / Sustainability | O6: Tích hợp vào vận hành | Q6: https://www.sixsenses.com/en/hotels-resorts/asia-the-pacific/vietnam/ninh-van-bay/sustainability/
A7: Six Senses Ninh Van Bay | B7: 2025 | C7: Waste & Plastic | D7: Reusable glass bottles | E7: 156.288 chai nhựa dùng một lần được thay thế bằng chai thủy tinh tái sử dụng. | F7: Core | G7: 156288 | H7: bottles | I7: B – Doanh nghiệp công bố định lượng | J7: Yes – Visible | K7: Output | L7: Đầu ra dễ hiểu và có thể so sánh nếu khu nghỉ dưỡng khác cũng công bố chai nhựa tránh dùng; chưa phải chất thải kết quả tổng thể. | M7: Evidence & Transparency; Integration | N7: F&B / Rooms / Sustainability | O7: Tích hợp liên phòng ban | P7: Trang chính thức của khu nghỉ dưỡng | Q7: https://www.sixsenses.com/en/hotels-resorts/asia-the-pacific/vietnam/ninh-van-bay/sustainability/
A8: Six Senses Ninh Van Bay | B8: 2025 | C8: Waste & Plastic | D8: Community Waste Care | E8: Trash to Treasure, Master Chef Upcycling, beach clean-ups và conservation activities thu hút 232 residents/hosts/guests và thu gom 1.961 kg rác. | F8: Supporting | G8: 1961 | H8: kg waste | I8: B – Doanh nghiệp công bố định lượng | J8: Yes – Participatory | K8: Output | L8: Vừa là hoạt động về chất thải vừa có cộng đồng/sự tham gia của khách; khía cạnh chính là Chất thải & Nhựa để tránh tính trùng. | M8: Community; Guest Experience; Integration | N8: Sustainability / Community / Experience | O8: Tích hợp với cộng đồng | P8: Trang chính thức của khu nghỉ dưỡng | Q8: https://www.sixsenses.com/en/hotels-resorts/asia-the-pacific/vietnam/ninh-van-bay/sustainability/
A9: Six Senses Ninh Van Bay | B9: 2025 | C9: Waste & Plastic | D9: Composting | E9: 4.200 kg phân hữu cơ/compost được sản xuất từ nguồn hữu cơ tại property trong năm 2025. | F9: Supporting | G9: 4200 | H9: kg | I9: B – Doanh nghiệp công bố định lượng | J9: No – Back-of-house | K9: Output | L9: Cho thấy tuần hoàn trong vận hành, nhưng chưa biết tỷ lệ rác hữu cơ được phân hữu cơ trên tổng chất thải. | M9: Integration; Evidence & Transparency | N9: F&B / Gardens / Sustainability | O9: Tích hợp vào vận hành | P9: Trang chính thức của khu nghỉ dưỡng | Q9: https://www.sixsenses.com/en/hotels-resorts/asia-the-pacific/vietnam/ninh-van-bay/sustainability/
A10: Six Senses Ninh Van Bay | B10: Current review | C10: Waste & Plastic | D10: Overall waste performance | E10: Có compost, bottles avoided và community waste outputs nhưng chưa thấy total waste generated, diversion rate hoặc waste/guest night. | F10: Data gap | I10: E – Chưa tìm thấy minh chứng cụ thể | J10: No – Back-of-house | K10: Data gap | L10: Quan trọng cho phần Thảo luận: nhiều đầu ra riêng lẻ không đồng nghĩa đã có chỉ số kết quả/hiệu suất tổng thể. | M10: Evidence & Transparency | N10: Engineering / Sustainability / F&B | O10: Tích hợp vào vận hành | Q10: https://www.sixsenses.com/en/hotels-resorts/asia-the-pacific/vietnam/ninh-van-bay/sustainability/
A11: Six Senses Ninh Van Bay | B11: 2025 | C11: Food & Procurement | D11: Organic gardens / Solar Fresh-Cuts | E11: Ba khu vườn sản xuất 13.849 kg rau quả hữu cơ; Solar Fresh-Cuts trồng herbs, fruits và vegetables dùng cho nhà hàng. | F11: Core | G11: 13849 | H11: kg | I11: B – Doanh nghiệp công bố định lượng | J11: Yes – Visible / experience-linked | K11: Output | L11: Một thực hành liên kết thu mua và F&B; phù hợp để phân tích tích hợp vào vận hành. | M11: Integration; Guest Experience | N11: F&B / Procurement / Sustainability | O11: Tích hợp liên phòng ban | P11: Trang chính thức của khu nghỉ dưỡng | Q11: https://www.sixsenses.com/en/hotels-resorts/asia-the-pacific/vietnam/ninh-van-bay/sustainability/
A12: Six Senses Ninh Van Bay | B12: Current | C12: Food & Procurement | D12: Responsible sourcing | E12: Property mô tả việc ưu tiên các nguồn nguyên liệu được khai thác/cung ứng có trách nhiệm trong hoạt động vận hành. | F12: Supporting | I12: C – Doanh nghiệp công bố định tính | J12: No – Back-of-house | K12: Practice | L12: Mô tả có ý nghĩa nhưng chưa có tỷ lệ địa phương/thu mua có trách nhiệm cụ thể. | M12: Evidence & Transparency | N12: Procurement / F&B / Sustainability | O12: Tích hợp vào vận hành | P12: Trang chính thức của khu nghỉ dưỡng | Q12: https://www.sixsenses.com/en/hotels-resorts/asia-the-pacific/vietnam/ninh-van-bay/sustainability/
A13: Six Senses Ninh Van Bay | B13: Current review | C13: Food & Procurement | D13: Local / responsible sourcing share | E13: Chưa tìm thấy % spending hoặc % food sourced locally/responsibly cho riêng Ninh Van Bay trong các nguồn đã rà. | F13: Data gap | I13: E – Chưa tìm thấy minh chứng cụ thể | J13: No – Back-of-house | K13: Data gap | L13: Giúp phân biệt thu mua commitment với mức độ thu mua được đo lường. | M13: Evidence & Transparency | N13: Procurement / F&B / Sustainability | O13: Tích hợp vào vận hành | Q13: https://www.sixsenses.com/en/hotels-resorts/asia-the-pacific/vietnam/ninh-van-bay/sustainability/
A14: Six Senses Ninh Van Bay | B14: 2019–2025 | C14: Biodiversity & Ecosystems | D14: Black-shanked douc langur population | E14: Property công bố số cá thể được ghi nhận tại Hòn Hèo tăng từ 109 năm 2019 lên 211 năm 2025. | F14: Core | G14: 211 | H14: individuals | I14: B – Doanh nghiệp công bố định lượng | J14: Yes – Experience-integrated | K14: Outcome indicator | L14: Gần kết quả hơn hoạt động/đầu ra, nhưng không được suy ra toàn bộ mức tăng là causal effect của khu nghỉ dưỡng. | M14: Evidence & Transparency; Interesting Case | N14: Sustainability / Biodiversity / Experience | O14: Tích hợp với khách / điểm đến | P14: Trang chính thức của khu nghỉ dưỡng | Q14: https://www.sixsenses.com/en/hotels-resorts/asia-the-pacific/vietnam/ninh-van-bay/sustainability/
A15: Six Senses Ninh Van Bay | B15: 2025 | C15: Biodiversity & Ecosystems | D15: Coral restoration | E15: Duy trì 80 coral frames, lắp 12 khung mới, cấy lại 200 coral fragments, hơn 250 giờ monitoring/maintenance; 128 guests tham gia. | F15: Core | G15: 200 | H15: coral fragments | I15: B – Doanh nghiệp công bố định lượng | J15: Yes – Participatory | K15: Output | L15: Rất giàu đầu ra chỉ sốs và có sự tham gia của khách; cần phân biệt phục hồi đầu ra với kết quả sinh thái. | M15: Guest Experience; Integration; Evidence & Transparency | N15: Marine / Sustainability / Experience | O15: Tích hợp với khách / điểm đến | P15: Trang chính thức của khu nghỉ dưỡng | Q15: https://www.sixsenses.com/en/hotels-resorts/asia-the-pacific/vietnam/ninh-van-bay/sustainability/
A16: Six Senses Ninh Van Bay | B16: 2019–2025 | C16: Biodiversity & Ecosystems | D16: Langur monitoring – partner corroboration | E16: GreenViet cũng báo cáo giám sát dài hạn cho thấy quần thể từ 109 cá thể năm 2019 lên 211 cá thể năm 2025. | F16: Core | G16: 211 | H16: individuals | I16: D – Xác nhận từ đối tác bên ngoài | J16: Yes – Experience-integrated | K16: Outcome indicator | L16: Nguồn đối tác corrobotỷ lệs xu hướng đối tượng; GreenViet là đối tác bảo tồn nên không gọi là independent audit. | M16: Evidence & Transparency | N16: Sustainability / Biodiversity / Research | O16: Tích hợp nghiên cứu / bảo tồn | P16: GreenViet | Q16: https://greenviet.org/tin-tuc/6-nam-dong-hanh-bao-ton-cha-va-chan-den-dau-an-hop-tac-greenviet-six-senses-ninh-van-bay/
A17: Six Senses Ninh Van Bay | B17: 2019–2024 | C17: Biodiversity & Ecosystems | D17: Five-year biodiversity survey | E17: GreenViet báo cáo hơn 300 loài động, thực vật được ghi nhận; 7 loài động vật và 10 loài thực vật thuộc các danh sách quý hiếm. | F17: Supporting | G17: 300 | H17: > species | I17: D – Xác nhận từ đối tác bên ngoài | J17: No – Research-facing | K17: Output | L17: Nguồn đối tác giúp đối chiếu quy mô nghiên cứu đa dạng sinh học; phạm vi khác với con số 150 loài do khu nghỉ dưỡng công bố từ năm 2022. | M17: Evidence & Transparency | N17: Biodiversity / Sustainability / Research | O17: Tích hợp nghiên cứu / bảo tồn | P17: GreenViet | Q17: https://greenviet.org/tin-tuc/thanh-tuu-xanh-tu-5-nam-hop-tac-giua-greenviet-va-six-senses-ninh-van-ba/
A18: Six Senses Ninh Van Bay | B18: 2022–2025 | C18: Biodiversity & Ecosystems | D18: Forest biodiversity research | E18: Six Senses công bố đã nhận diện 150 species trong surrounding forest từ 2022, gồm 10 rare plant species; Curcuma sixsensesensis được công nhận năm 2022. | F18: Supporting | G18: 150 | H18: species | I18: B – Doanh nghiệp công bố định lượng | J18: No – Research-facing | K18: Output | L18: Không gộp trực tiếp với số 300+ loài của GreenViet vì phạm vi/thời kỳ khác. | M18: Evidence & Transparency | N18: Biodiversity / Sustainability / Research | O18: Tích hợp nghiên cứu / bảo tồn | P18: Trang chính thức của khu nghỉ dưỡng | Q18: https://www.sixsenses.com/en/hotels-resorts/asia-the-pacific/vietnam/ninh-van-bay/sustainability/
A19: Six Senses Ninh Van Bay | B19: 2025 | C19: Biodiversity & Ecosystems | D19: Mangrove restoration | E19: Six Senses công bố hơn 150 hosts tham gia trồng 14.700 cây ngập mặn tại Đầm Bấy và Đầm Thị Nại. | F19: Supporting | G19: 14700 | H19: trees | I19: B – Doanh nghiệp công bố định lượng | J19: No – Staff/community-facing | K19: Output | L19: Đầu ra phục hồi hệ sinh thái; chưa phải kết quả như survival tỷ lệ hoặc đa dạng sinh học change. | M19: Integration; Community | N19: Sustainability / HR / Community | O19: Tích hợp liên phòng ban | P19: Trang chính thức của khu nghỉ dưỡng | Q19: https://www.sixsenses.com/en/hotels-resorts/asia-the-pacific/vietnam/ninh-van-bay/sustainability/
A20: Six Senses Ninh Van Bay | B20: 2025 | C20: Biodiversity & Ecosystems | D20: Natural coral spawning | E20: Ngày 18/4/2025, resort lần đầu ghi nhận hiện tượng sinh sản tự nhiên của san hô trong restoration area. | F20: Supporting | G20: 1 | H20: recorded event | I20: B – Doanh nghiệp công bố định lượng | J20: No – Research-facing | K20: Outcome indicator | L20: Đây là chỉ báo thay đổi sinh thái đáng chú ý, nhưng một lần quan sát chưa đủ để chứng minh tác động dài hạn. | M20: Interesting Case; Evidence & Transparency | N20: Marine Biology / Sustainability | O20: Tích hợp nghiên cứu / bảo tồn | P20: Trang chính thức của khu nghỉ dưỡng | Q20: https://www.sixsenses.com/en/hotels-resorts/asia-the-pacific/vietnam/ninh-van-bay/sustainability/
A21: Six Senses Ninh Van Bay | B21: 2019–2025 | C21: Biodiversity & Ecosystems | D21: Camera-trap wildlife monitoring | E21: GreenViet ghi nhận các loài quý hiếm qua camera trap như Cheo cheo lưng bạc, Tê tê Java, Cu li nhỏ/Mèo rừng; giai đoạn 2023–2025 tiếp tục có wildlife records. | F21: Appendix | I21: D – Xác nhận từ đối tác bên ngoài | J21: No – Research-facing | K21: Output | L21: Cho thấy hoạt động theo dõi khoa học kéo dài, nhưng chưa có một KPI tổng hợp duy nhất để so sánh. | M21: Interesting Case; Evidence & Transparency | N21: Biodiversity / Research | O21: Tích hợp nghiên cứu / bảo tồn | P21: GreenViet | Q21: https://greenviet.org/tin-tuc/thanh-tuu-xanh-tu-5-nam-hop-tac-giua-greenviet-va-six-senses-ninh-van-ba/
A22: Six Senses Ninh Van Bay | B22: 2025 | C22: Community & People | D22: Education empowerment | E22: Hơn 1.000 students hưởng lợi từ educational programs; 138 university students tham gia sustainability workshops; 400 books được tặng. | F22: Core | G22: 1000 | H22: > students | I22: B – Doanh nghiệp công bố định lượng | J22: No – Community-facing | K22: Output | L22: Có đầu ra xã hội rõ nhưng chưa có longitudinal kết quả về việc làm/income/nghề nghiệp progression. | M22: Community; Evidence & Transparency | N22: HR / Education / Community / Sustainability | O22: Tích hợp với cộng đồng | P22: Trang chính thức của khu nghỉ dưỡng | Q22: https://www.sixsenses.com/en/hotels-resorts/asia-the-pacific/vietnam/ninh-van-bay/sustainability/
A23: Six Senses Ninh Van Bay | B23: H1 2025 | C23: Community & People | D23: Staff conservation training | E23: GreenViet ghi nhận 6 hoạt động nội bộ về biodiversity/conservation, thu hút tổng cộng 62 nhân viên tham gia. | F23: Core | G23: 62 | H23: staff | I23: D – Xác nhận từ đối tác bên ngoài | J23: No – Staff-facing | K23: Output | L23: Minh chứng tốt cho góc nhìn quản lý/tích hợp: nhân viên được trang bị kiến thức để truyền tải tới khách. | M23: Integration; Community | N23: HR / Sustainability / Experience | O23: Tích hợp liên phòng ban | P23: GreenViet | Q23: https://greenviet.org/tin-tuc/truyen-cam-hung-yeu-va-bao-ve-thien-nhien-tai-six-senses-ninh-van-bay/
A24: Six Senses Ninh Van Bay | B24: 2025 | C24: Community & People | D24: Water for All | E24: Lắp hệ thống RO–UV tại Ninh Ich Primary School, cung cấp nước uống an toàn cho 200 students & teachers; awareness sessions cho hơn 180 người. | F24: Core | G24: 200 | H24: students & teachers | I24: B – Doanh nghiệp công bố định lượng | J24: No – Community-facing | K24: Output | L24: khía cạnh chính là cộng đồng & People vì đây là cộng đồng access project, không phải KPI sử dụng nước trong khu nghỉ dưỡng. | M24: Community; Evidence & Transparency | N24: Community / Sustainability / Water | O24: Tích hợp với cộng đồng | P24: Trang chính thức của khu nghỉ dưỡng | Q24: https://www.sixsenses.com/en/hotels-resorts/asia-the-pacific/vietnam/ninh-van-bay/sustainability/
A25: Six Senses Ninh Van Bay | B25: 2025 | C25: Community & People | D25: Conservation awareness for local community & students | E25: Six Senses công bố 457 người dân địa phương và học sinh/sinh viên tham gia reforestation, school visits, university presentations, wildlife education và Earth Day exhibitions. | F25: Supporting | G25: 457 | H25: people | I25: B – Doanh nghiệp công bố định lượng | J25: No – Community-facing | K25: Output | L25: Không gộp với con số 457 sự tham gia của kháchs do GreenViet công bố; hai nguồn mô tả khác đối tượng. | M25: Community; Evidence & Transparency | N25: Sustainability / Community / Education | O25: Tích hợp với cộng đồng | P25: Trang chính thức của khu nghỉ dưỡng | Q25: https://www.sixsenses.com/en/hotels-resorts/asia-the-pacific/vietnam/ninh-van-bay/sustainability/
A26: Six Senses Ninh Van Bay | B26: 2024–2025 | C26: Community & People | D26: Solar for Life | E26: Năm 2025 lắp 18 hệ thống đèn năng lượng mặt trời; Six Senses cho biết dự án mang lợi ích cho hơn 1.330 người trong 2024–2025. | F26: Supporting | G26: 1330 | H26: > people benefited | I26: B – Doanh nghiệp công bố định lượng | J26: No – Community-facing | K26: Output | L26: Dùng cộng đồng & People làm khía cạnh chính vì chỉ số chính là người hưởng lợi reach, dù giải pháp dùng điện mặt trời. | M26: Community; Integration | N26: Community / Sustainability | O26: Tích hợp với cộng đồng | P26: Trang chính thức của khu nghỉ dưỡng | Q26: https://www.sixsenses.com/vn/hotels-resorts/asia-the-pacific/vietnam/ninh-van-bay/sustainability/
A27: Six Senses Ninh Van Bay | B27: H1 2025 | C27: Community & People | D27: Student environmental field trip | E27: GreenViet ghi nhận 2 chương trình giáo dục cho học sinh; tiêu biểu có 26 học sinh và giáo viên của Happy Village School tham gia field trip. | F27: Supporting | G27: 26 | H27: students & teachers | I27: D – Xác nhận từ đối tác bên ngoài | J27: Yes – Participatory | K27: Output | L27: đối tác corroboration cho social/cộng đồng dimension. | M27: Community | N27: Sustainability / Education / Community | O27: Tích hợp với cộng đồng | P27: GreenViet | Q27: https://greenviet.org/tin-tuc/truyen-cam-hung-yeu-va-bao-ve-thien-nhien-tai-six-senses-ninh-van-bay/
A28: Six Senses Ninh Van Bay | B28: Current review | C28: Community & People | D28: Local workforce / employment outcome | E28: Property nói có scholarships, internships và employment opportunities nhưng chưa thấy % local workforce, retention hoặc career outcome dài hạn. | F28: Data gap | I28: E – Chưa tìm thấy minh chứng cụ thể | J28: No – Back-of-house | K28: Data gap | L28: Giúp kiểm tra social phát triển bền vững có đi từ programme đầu ra tới việc làm kết quả hay chưa. | M28: Community; Evidence & Transparency | N28: HR / Community / Sustainability | O28: Tích hợp ở hệ thống quản lý | Q28: https://www.sixsenses.com/en/hotels-resorts/asia-the-pacific/vietnam/ninh-van-bay/sustainability/
A29: Six Senses Ninh Van Bay | B29: Current | C29: Culture & Heritage | D29: Local culture interpretation at Earth Lab / Langur Lounge | E29: Property mô tả Earth Lab và Langur Lounge là nơi du khách tìm hiểu về sustainability, local culture và wildlife conservation. | F29: Supporting | I29: C – Doanh nghiệp công bố định tính | J29: Yes – Experience-integrated | K29: Practice | L29: Có mô tả việc giới thiệu văn hóa, nhưng nguồn đã rà chưa cung cấp thực hành/chỉ số văn hóa cụ thể hơn. | M29: Breadth; Guest Experience; Evidence & Transparency | N29: Experience / Sustainability / Culture | O29: Tích hợp vào trải nghiệm khách | P29: Trang chính thức của khu nghỉ dưỡng | Q29: https://www.sixsenses.com/en/hotels-resorts/asia-the-pacific/vietnam/ninh-van-bay/sustainability/
A30: Six Senses Ninh Van Bay | B30: Current review | C30: Culture & Heritage | D30: Cultural heritage outcomes / metrics | E30: Trong các nguồn đã rà, chưa tìm thấy metric hoặc outcome cụ thể về bảo tồn di sản/văn hóa địa phương tại property. | F30: Data gap | I30: E – Chưa tìm thấy minh chứng cụ thể | J30: No – Governance | K30: Data gap | L30: Không có công khai minh chứng cụ thể không đồng nghĩa khu nghỉ dưỡng không thực hiện; chỉ phản ánh công bố được tìm thấy. | M30: Breadth; Evidence & Transparency | N30: Culture / Experience / Sustainability | O30: Tích hợp vào trải nghiệm khách | Q30: https://www.sixsenses.com/en/hotels-resorts/asia-the-pacific/vietnam/ninh-van-bay/sustainability/
A31: Six Senses Ninh Van Bay | B31: H1 2025 | C31: Guest Engagement | D31: Langur Discovery | E31: Khoảng 117 guests tham gia Langur Discovery do GreenViet researchers hướng dẫn trong 6 tháng đầu 2025. | F31: Core | G31: 117 | H31: guests | I31: D – Xác nhận từ đối tác bên ngoài | J31: Yes – Participatory | K31: Output | L31: Minh chứng trực tiếp từ đối tác về trải nghiệm phát triển bền vững có sự tham gia của khách. | M31: Guest Experience; Integration | N31: Experience / Biodiversity / Sustainability | O31: Tích hợp vào trải nghiệm khách | P31: GreenViet | Q31: https://greenviet.org/tin-tuc/truyen-cam-hung-yeu-va-bao-ve-thien-nhien-tai-six-senses-ninh-van-bay/
A32: Six Senses Ninh Van Bay | B32: 2025 | C32: Guest Engagement | D32: Nature experiences – annual participation | E32: GreenViet báo cáo 457 lượt du khách tham gia Step into the Wild, Langur Talk, Flora Walk hoặc Nature Hike trong năm 2025. | F32: Core | G32: 457 | H32: guest participations | I32: D – Xác nhận từ đối tác bên ngoài | J32: Yes – Participatory | K32: Output | L32: Không gộp với con số 457 người dân địa phương/học sinh, sinh viên do Six Senses công bố; đây là lượt khách tham gia theo GreenViet. | M32: Guest Experience; Evidence & Transparency | N32: Experience / Biodiversity / Sustainability | O32: Tích hợp vào trải nghiệm khách | P32: GreenViet | Q32: https://greenviet.org/tin-tuc/6-nam-dong-hanh-bao-ton-cha-va-chan-den-dau-an-hop-tac-greenviet-six-senses-ninh-van-bay/
A33: Six Senses Ninh Van Bay | B33: H1 2025 | C33: Guest Engagement | D33: Nature learning activities | E33: Khoảng 97 guests tham gia Langur Talk, Flora Walk, Snake Talk và Nature Hike. | F33: Supporting | G33: 97 | H33: guests | I33: D – Xác nhận từ đối tác bên ngoài | J33: Yes – Participatory | K33: Output | L33: Cho thấy phát triển bền vững được đóng gói thành trải nghiệm học hỏi, không chỉ truyền thông thụ động. | M33: Guest Experience; Integration | N33: Experience / Biodiversity | O33: Tích hợp vào trải nghiệm khách | P33: GreenViet | Q33: https://greenviet.org/tin-tuc/truyen-cam-hung-yeu-va-bao-ve-thien-nhien-tai-six-senses-ninh-van-bay/
A34: InterContinental Danang Sun Peninsula Resort | B34: 2026–2027 | C34: Energy & Climate | D34: Monthly energy monitoring & efficiency | E34: Sustainability Management Plan nêu resort theo dõi mức sử dụng năng lượng hàng tháng và ưu tiên thiết bị/giải pháp tiết kiệm năng lượng. | F34: Supporting | I34: C – Doanh nghiệp công bố định tính | J34: No – Back-of-house | K34: Practice | L34: Có quy trình quản lý rõ nhưng chưa thấy KPI cường độ sử dụng năng lượng/cấp khu nghỉ dưỡng mức giảm cụ thể trong nguồn này. | M34: Integration; Evidence & Transparency | N34: Engineering / Sustainability | O34: Tích hợp vào vận hành | P34: Kế hoạch Quản lý Phát triển bền vững của khu nghỉ dưỡng | Q34: https://www.danang.intercontinental.com/wp-content/uploads/2025/11/SUSTAINABILITY-MANAGEMENT-PLAN-2026-2027.pdf
A35: InterContinental Danang Sun Peninsula Resort | B35: 2026–2027 | C35: Water | D35: Water saving, reuse & wastewater management | E35: Plan nêu giám sát nguồn nước/nước thải, dùng thiết bị tiết kiệm nước, tái sử dụng nước phù hợp và khuyến khích towel/linen reuse. | F35: Core | I35: C – Doanh nghiệp công bố định tính | J35: Mixed | K35: Practice | L35: Thể hiện quản lý nước đã đi vào vận hành và khách hành vi, nhưng chưa có cường độ sử dụng nước KPI công khai trong nguồn rà soát. | M35: Integration; Guest Experience; Evidence & Transparency | N35: Engineering / Housekeeping / Rooms / Sustainability | O35: Tích hợp liên phòng ban | P35: Kế hoạch Quản lý Phát triển bền vững của khu nghỉ dưỡng | Q35: https://www.danang.intercontinental.com/wp-content/uploads/2025/11/SUSTAINABILITY-MANAGEMENT-PLAN-2026-2027.pdf
A36: InterContinental Danang Sun Peninsula Resort | B36: 2026 | C36: Water | D36: Chlorine-free outdoor pools / salt ionizer | E36: Green Globe reports chlorine was removed from outdoor swimming pools and a salt-ionizer system installed to reduce environmental impacts while maintaining water quality. | F36: Supporting | I36: D – Xác nhận từ nguồn chứng nhận bên ngoài | J36: Yes – Visible | K36: Practice | L36: Nguồn chứng nhận bên ngoài xác nhận một biện pháp xử lý nước cụ thể; đây không phải KPI về lượng nước tiêu thụ. | M36: Integration; Evidence & Transparency | N36: Engineering / Pools / Sustainability | O36: Tích hợp vào vận hành | P36: Green Globe | Q36: https://www.greenglobe.com/news/intercontinental-danang-sun-peninsula-resort
A37: InterContinental Danang Sun Peninsula Resort | B37: 2026–2027 | C37: Waste & Plastic | D37: Triple R / organic waste reuse / glass bottles | E37: Plan nêu food và organic waste được tái sử dụng cho farming, áp dụng Triple R, theo dõi waste output hàng tháng và dùng nước uống trong chai thủy tinh. | F37: Core | I37: C – Doanh nghiệp công bố định tính | J37: Yes – Visible | K37: Practice | L37: thực hành trải qua F&B, quản lý chất thải và bao bì dành cho khách; chưa thấy tổng tỷ lệ chuyển hướng chất thải. | M37: Integration; Guest Experience; Evidence & Transparency | N37: F&B / Engineering / Housekeeping / Sustainability | O37: Tích hợp liên phòng ban | P37: Kế hoạch Quản lý Phát triển bền vững của khu nghỉ dưỡng | Q37: https://www.danang.intercontinental.com/wp-content/uploads/2025/11/SUSTAINABILITY-MANAGEMENT-PLAN-2026-2027.pdf
A38: InterContinental Danang Sun Peninsula Resort | B38: 2026–2027 | C38: Food & Procurement | D38: Responsible/local purchasing & endangered-species No-No list | E38: Plan ưu tiên hàng tái chế/tái chế được, local suppliers và giảm chemical footprint; F&B có 'No-No list' nhằm tránh các loài nguy cấp. | F38: Core | I38: C – Doanh nghiệp công bố định tính | J38: Yes – Visible / experience-linked | K38: Practice | L38: Cho thấy thu mua và F&B được đưa vào phát triển bền vững khung; chưa có % địa phương thu mua. | M38: Breadth; Integration | N38: Procurement / F&B / Sustainability | O38: Tích hợp liên phòng ban | P38: Kế hoạch Quản lý Phát triển bền vững của khu nghỉ dưỡng | Q38: https://www.danang.intercontinental.com/wp-content/uploads/2025/11/SUSTAINABILITY-MANAGEMENT-PLAN-2026-2027.pdf
A39: InterContinental Danang Sun Peninsula Resort | B39: Current | C39: Biodiversity & Ecosystems | D39: Monkey bridges & native habitat support | E39: Trang Nature & Wildlife mô tả 5 monkey bridges, habitat planting và các biện pháp giảm xung đột giữa resort operations với wildlife tại Sơn Trà. | F39: Core | G39: 5 | H39: monkey bridges | I39: B – Doanh nghiệp công bố định lượng | J39: Yes – Visible | K39: Output | L39: chỉ số là hạ tầng hỗ trợ wildlife, không phải kết quả của quần thể động vật. | M39: Integration; Guest Experience | N39: Sustainability / Engineering / Landscaping / Experience | O39: Tích hợp liên phòng ban | P39: Trang Thiên nhiên & Động vật hoang dã chính thức của khu nghỉ dưỡng | Q39: https://www.danang.intercontinental.com/sustainability/nature-wildlife/
A40: InterContinental Danang Sun Peninsula Resort | B40: Current | C40: Biodiversity & Ecosystems | D40: Surrounding nature-reserve biodiversity context | E40: Property environmental page states the surrounding nature reserve supports more than 1,500 species of flora and fauna. | F40: Appendix | G40: 1500 | H40: > species in surrounding reserve | I40: B – Doanh nghiệp công bố định lượng | J40: No – Context | K40: Output / context | L40: Đây là bối cảnh cho thấy độ nhạy sinh thái của khu vực, không phải kết quả đa dạng sinh học do khu nghỉ dưỡng tạo ra và không nhất thiết là số loài ghi nhận trong ranh giới khu nghỉ dưỡng. | M40: Biodiversity; Evidence & Transparency | N40: Sustainability / Landscaping / Destination | O40: Bối cảnh điểm đến | P40: Cam kết Môi trường của khu nghỉ dưỡng | Q40: https://www.danang.intercontinental.com/sustainability/environmental-commitment/
A41: InterContinental Danang Sun Peninsula Resort | B41: 2026–2027 | C41: Community & People | D41: Local hiring, training & hospitality-school collaboration | E41: Sociocultural plan nêu ưu tiên local hiring, employee training và hợp tác với các trường hospitality để phát triển năng lực/việc làm. | F41: Core | I41: C – Doanh nghiệp công bố định tính | J41: No – Staff-facing | K41: Practice | L41: Có tích hợp vào hoạt động nhân sự nhưng chưa thấy KPI công khai về tỷ lệ lao động địa phương hay kết quả việc làm. | M41: Breadth; Community; Evidence & Transparency | N41: HR / Community / Learning & Development | O41: Tích hợp liên phòng ban | P41: Cam kết Xã hội – Văn hóa của khu nghỉ dưỡng | Q41: https://www.danang.intercontinental.com/sustainability/sociocultural-commitment/
A42: InterContinental Danang Sun Peninsula Resort | B42: Current | C42: Community & People | D42: Community support & clean-water initiatives | E42: Trang Local Community mô tả hỗ trợ bệnh viện, trung tâm dạy nghề/nhóm yếu thế, hiến máu và hệ thống lọc nước sạch cho cộng đồng địa phương. | F42: Supporting | I42: C – Doanh nghiệp công bố định tính | J42: No – Community-facing | K42: Practice | L42: Phù hợp để minh họa khía cạnh xã hội của phát triển bền vững; chưa nên gộp các chương trình thành một kết quả duy nhất. | M42: Community; Breadth | N42: Community / HR / Sustainability | O42: Tích hợp với cộng đồng | P42: Trang Cộng đồng địa phương chính thức của khu nghỉ dưỡng | Q42: https://www.danang.intercontinental.com/sustainability/local-community/
A43: InterContinental Danang Sun Peninsula Resort | B43: 2026–2027 | C43: Culture & Heritage | D43: Local culture, art & architecture interpretation | E43: Resort cam kết cung cấp thông tin về văn hóa/lịch sử/thiên nhiên địa phương và phản ánh local art/architecture trong thiết kế, trải nghiệm. | F43: Supporting | I43: C – Doanh nghiệp công bố định tính | J43: Yes – Experience-integrated | K43: Practice | L43: Mức độ tích hợp văn hóa được mô tả khá rõ nhưng chưa có chỉ số/kết quả cụ thể. | M43: Breadth; Guest Experience; Evidence & Transparency | N43: Design / Experience / Communications | O43: Tích hợp vào trải nghiệm khách | P43: Cam kết Xã hội – Văn hóa của khu nghỉ dưỡng | Q43: https://www.danang.intercontinental.com/sustainability/sociocultural-commitment/
A44: InterContinental Danang Sun Peninsula Resort | B44: Prior year reported by Green Globe | C44: Guest Engagement | D44: Nature education participation | E44: Green Globe reports that more than 6,500 participants attended nature-education activities such as Nature Expeditions and daily Ecowalks in the preceding year. | F44: Core | G44: 6500 | H44: participants (>) | I44: D – Xác nhận từ đối tác bên ngoài | J44: Yes – Participatory | K44: Output | L44: Nguồn bên ngoài giúp đối chiếu hoạt động gắn kết khách. Bài viết không cho thấy phương pháp đếm lượt tham gia đã được kiểm toán độc lập. | M44: Guest Experience; Evidence & Transparency | N44: Experience / Sustainability / Biodiversity | O44: Tích hợp vào trải nghiệm khách | P44: Green Globe | Q44: https://www.greenglobe.com/news/intercontinental-danang-sun-peninsula-resort
A45: InterContinental Danang Sun Peninsula Resort | B45: Current | C45: Guest Engagement | D45: Resident naturalist wildlife education | E45: Resort tổ chức các nature/wildlife tours với resident naturalist; Primate Appreciation Month được giới thiệu từ 2025 như hoạt động giáo dục định kỳ. | F45: Core | I45: C – Doanh nghiệp công bố định tính | J45: Yes – Participatory | K45: Practice | L45: Minh chứng trực tiếp cho việc phát triển bền vững/bảo tồn thiên nhiên trở thành một phần của trải nghiệm khách. | M45: Guest Experience; Integration | N45: Experience / Sustainability / Biodiversity | O45: Tích hợp vào trải nghiệm khách | P45: Trang Thiên nhiên & Động vật hoang dã chính thức của khu nghỉ dưỡng | Q45: https://www.danang.intercontinental.com/sustainability/nature-wildlife/
A46: Banyan Tree Lang Co | B46: Current review | C46: Energy & Climate | D46: Property-level energy performance | E46: Trong các nguồn property-level đã rà, chưa tìm thấy KPI energy intensity/carbon performance riêng cho Banyan Tree Lang Co. | F46: Data gap | I46: E – Chưa tìm thấy minh chứng cụ thể | J46: No – Back-of-house | K46: Data gap | L46: Laguna Lăng Cô có dữ liệu phát triển bền vững ở cấp khu phức hợp, nhưng không nên tự động gán toàn bộ số liệu này cho Banyan Tree Lang Co. | M46: Evidence & Transparency | N46: Engineering / Sustainability | O46: Tích hợp ở hệ thống quản lý | Q46: https://www.banyantree.com/vietnam/lang-co/sustainability
A47: Banyan Tree Lang Co | B47: Current review | C47: Water | D47: Property-level water performance | E47: No current property-specific water intensity, annual consumption, reuse share or wastewater KPI was located in the Banyan Tree Lang Co public sources reviewed. Laguna Lang Co publishes integrated-resort metrics separately. | F47: Data gap | I47: E – Chưa tìm thấy minh chứng cụ thể | J47: No – Back-of-house | K47: Data gap | L47: Tách riêng với số liệu hạ tầng của khu phức hợp Laguna Lăng Cô để tránh gán sai phạm vi. | M47: Evidence & Transparency | N47: Engineering / Sustainability | O47: Tích hợp ở hệ thống quản lý | P47: Rà soát nghiên cứu | Q47: https://www.banyantree.com/vietnam/lang-co/sustainability
A48: Banyan Tree Lang Co | B48: Current integrated-resort disclosure | C48: Water | D48: Laguna Lăng Cô integrated-resort water metrics | E48: Laguna Lăng Cô công bố ở cấp integrated resort: 141.185 m³ wastewater được xử lý tại chỗ; 67% water consumption đến từ alternative water supplies. Không có breakdown riêng cho Banyan Tree Lang Co. | F48: Appendix | G48: 141185 | H48: m³ wastewater treated | I48: B – Doanh nghiệp công bố định lượng | J48: No – Back-of-house | K48: Output | L48: Phạm vi là toàn Laguna Lăng Cô; KHÔNG dùng chỉ số này như khu nghỉ dưỡng-KPI cụ thể của Banyan Tree. Có thể dùng để minh họa phát triển bền vững hạ tầng chung của điểm đến. | M48: Evidence & Transparency; Integration | N48: Engineering / Sustainability | O48: Tích hợp liên phòng ban | P48: Khu phức hợp Laguna Lăng Cô | Q48: https://www.lagunalangco.com/sustainability/
A49: Banyan Tree Lang Co | B49: Current review | C49: Waste & Plastic | D49: Property-level waste / plastic performance | E49: No current Banyan Tree Lang Co-specific waste diversion, plastic reduction, compost or packaging KPI was located in the property sources reviewed; Laguna Lang Co reports destination-level data separately. | F49: Data gap | I49: E – Chưa tìm thấy minh chứng cụ thể | J49: No – Back-of-house | K49: Data gap | L49: Khoảng trống công bố ở cấp khu nghỉ dưỡng; không thay bằng số liệu của toàn khu phức hợp. | M49: Evidence & Transparency | N49: Housekeeping / F&B / Sustainability | O49: Tích hợp ở hệ thống quản lý | P49: Rà soát nghiên cứu | Q49: https://www.banyantree.com/vietnam/lang-co/sustainability
A50: Banyan Tree Lang Co | B50: Current integrated-resort disclosure | C50: Waste & Plastic | D50: Laguna Lăng Cô integrated-resort bottling / compost metrics | E50: Laguna Lăng Cô công bố ở cấp integrated resort: 445.627 glass bottles được sản xuất on-site và 909 tấn compost được tạo từ organic waste. Không có breakdown riêng cho Banyan Tree Lang Co. | F50: Appendix | G50: 445627 | H50: glass bottles produced on-site | I50: B – Doanh nghiệp công bố định lượng | J50: Yes – Visible | K50: Output | L50: Phạm vi là toàn Laguna Lăng Cô; giữ làm bối cảnh, không so sánh trực tiếp với cấp khu nghỉ dưỡng KPI chất thải của khu nghỉ dưỡng khác. | M50: Evidence & Transparency; Integration | N50: Engineering / F&B / Sustainability | O50: Tích hợp liên phòng ban | P50: Khu phức hợp Laguna Lăng Cô | Q50: https://www.lagunalangco.com/sustainability/
A51: Banyan Tree Lang Co | B51: Current review | C51: Food & Procurement | D51: Property-level responsible/local sourcing metric | E51: No property-specific percentage or quantified current KPI for local/responsible food procurement was located in the reviewed Banyan Tree Lang Co public pages. | F51: Data gap | I51: E – Chưa tìm thấy minh chứng cụ thể | J51: No – Back-of-house | K51: Data gap | L51: Giữ để phân biệt cam kết thu mua với kết quả thu mua đã được đo lường. | M51: Evidence & Transparency | N51: Procurement / F&B / Sustainability | O51: Tích hợp ở hệ thống quản lý | P51: Rà soát nghiên cứu | Q51: https://www.banyantree.com/vietnam/lang-co/sustainability
A52: Banyan Tree Lang Co | B52: Current | C52: Biodiversity & Ecosystems | D52: 15 Signature Birds / guided birdwatching | E52: Banyan Tree Lang Co's biodiversity experience highlights 15 Signature Birds and offers complimentary guided birdwatching three days per week. | F52: Core | G52: 15 | H52: signature bird species | I52: B – Doanh nghiệp công bố định lượng | J52: Yes – Participatory | K52: Output / practice | L52: Có số liệu định lượng cho trải nghiệm đa dạng sinh học dành cho khách, nhưng đây không phải chỉ báo kết quả về quần thể sinh thái. | M52: Guest Experience; Biodiversity; Integration | N52: Experience / Sustainability / Biodiversity | O52: Tích hợp vào trải nghiệm khách | P52: Trang đa dạng sinh học của Banyan Tree Lang Co | Q52: https://www.banyantree.com/vietnam/lang-co/biodiversity-at-banyan-tree-lang-co
A53: Banyan Tree Lang Co | B53: Current | C53: Biodiversity & Ecosystems | D53: Birdwatching / biodiversity experiences | E53: Stay for Good có các hoạt động quan sát chim và khám phá thiên nhiên/biodiversity trong destination. | F53: Supporting | I53: C – Doanh nghiệp công bố định tính | J53: Yes – Participatory | K53: Practice | L53: Dành cho khách đa dạng sinh học minh chứng; chưa phải kết quả sinh thái. | M53: Guest Experience; Biodiversity | N53: Experience / Sustainability | O53: Tích hợp vào trải nghiệm khách | P53: Banyan Tree Lang Co Stay for Good | Q53: https://www.banyantree.com/vietnam/lang-co/experiences/stay-for-good
A54: Banyan Tree Lang Co | B54: Since 2015 | C54: Community & People | D54: Seedlings Mentorship | E54: Property mô tả chương trình Seedlings Mentorship hỗ trợ school fees/supplies và mentors cho trẻ em địa phương đến tuổi 18. | F54: Core | I54: C – Doanh nghiệp công bố định tính | J54: No – Community-facing | K54: Practice | L54: Cho thấy social phát triển bền vững đi theo hướng phát triển dài hạn thay vì chỉ donation một lần; chưa thấy kết quả học tập dài hạn. | M54: Community; Breadth; Evidence & Transparency | N54: Community / Sustainability / HR | O54: Tích hợp với cộng đồng | P54: Banyan Tree Lang Co Sustainability | Q54: https://www.banyantree.com/vietnam/lang-co/sustainability
A55: Banyan Tree Lang Co | B55: Current | C55: Community & People | D55: Seedlings vocational training | E55: Chương trình đào tạo nghề dành cho thanh niên khó khăn 18–24 tuổi, hướng tới kỹ năng nghề và cơ hội việc làm. | F55: Core | I55: C – Doanh nghiệp công bố định tính | J55: No – Community-facing | K55: Practice | L55: Có link rõ với human capital/việc làm nhưng chưa thấy số học viên hoặc placement tỷ lệ công khai trên trang. | M55: Community; Breadth; Evidence & Transparency | N55: Community / HR / Learning & Development | O55: Tích hợp với cộng đồng | P55: Banyan Tree Lang Co Sustainability | Q55: https://www.banyantree.com/vietnam/lang-co/sustainability
A56: Banyan Tree Lang Co | B56: Since 2015 | C56: Community & People | D56: Nuoc Ngot Social Protection Center / livelihood support | E56: Property mô tả hợp tác với Nuoc Ngot Social Protection Center; một hướng hỗ trợ sinh kế là trồng Melaleuca để tạo nguyên liệu tinh dầu. | F56: Supporting | I56: C – Doanh nghiệp công bố định tính | J56: No – Community-facing | K56: Practice | L56: Một example về cộng đồng sinh kế; chưa có income/chỉ số kết quả. | M56: Community; Integration | N56: Community / Sustainability | O56: Tích hợp với cộng đồng | P56: Banyan Tree Lang Co Sustainability | Q56: https://www.banyantree.com/vietnam/lang-co/sustainability
A57: Banyan Tree Lang Co | B57: Current | C57: Culture & Heritage | D57: Local craft & cultural experiences | E57: Stay for Good giới thiệu các hoạt động thủ công/câu chuyện địa phương gắn với cộng đồng và trải nghiệm khách. | F57: Core | I57: C – Doanh nghiệp công bố định tính | J57: Yes – Participatory | K57: Practice | L57: Có tích hợp yếu tố văn hóa nhưng trang công khai chưa cung cấp kết quả định lượng về văn hóa. | M57: Breadth; Guest Experience; Community | N57: Experience / Culture / Community | O57: Tích hợp vào trải nghiệm khách | P57: Banyan Tree Lang Co Stay for Good | Q57: https://www.banyantree.com/vietnam/lang-co/experiences/stay-for-good
A58: Banyan Tree Lang Co | B58: Current | C58: Guest Engagement | D58: Stay for Good experiences | E58: Banyan Tree Lang Co đưa các hoạt động Stay for Good vào trải nghiệm khách, gồm craft/community và nature-oriented experiences. | F58: Core | I58: C – Doanh nghiệp công bố định tính | J58: Yes – Participatory | K58: Practice | L58: Cho thấy phát triển bền vững/cộng đồng không chỉ ở back-of-house mà được chuyển thành trải nghiệm khách. | M58: Guest Experience; Integration | N58: Experience / Community / Sustainability | O58: Tích hợp vào trải nghiệm khách | P58: Banyan Tree Lang Co Stay for Good | Q58: https://www.banyantree.com/vietnam/lang-co/experiences/stay-for-good
A59: Topas Ecolodge | B59: Current | C59: Energy & Climate | D59: Low-energy operation & hydropower reliance | E59: Topas describes low-energy operations and use of renewable sources; the 2026 ASEAN Green Hotel disclosure specifically notes solar-energy application in operations. | F59: Core | I59: C – Doanh nghiệp công bố định tính | J59: No – Back-of-house | K59: Practice | L59: Có mô tả rõ thực hành năng lượng tái tạo/tiết kiệm, nhưng chưa công bố KPI hiện tại về kWh, cường độ năng lượng hoặc carbon. | M59: Integration; Evidence & Transparency | N59: Engineering / Operations | O59: Tích hợp vào vận hành | P59: Topas Sustainable Development + ASEAN Green Hotel 2026 page | Q59: https://topasecolodge.com/topas-ecolodge-recognized-as-asean-green-hotel-2026/
A60: Topas Ecolodge | B60: Current | C60: Water | D60: Rainwater, greywater & constructed-wetland treatment | E60: Topas describes rainwater collection/treatment, greywater reuse and wastewater treatment. Its 2026 award disclosure also states Hydroloop drinking-water testing in Sep 2025 met QCVN 01-1:2024/BYT indicators. | F60: Core | I60: C – Doanh nghiệp công bố định tính | J60: No – Back-of-house | K60: Practice | L60: Hệ thống nước được mô tả rõ, nhưng nguồn công khai vẫn chưa cung cấp tổng lượng nước sử dụng hoặc cường độ nước. | M60: Integration; Evidence & Transparency | N60: Engineering / Housekeeping / F&B | O60: Tích hợp liên phòng ban | P60: Topas Sustainable Development + ASEAN Green Hotel 2026 disclosure | Q60: https://topasecolodge.com/topas-ecolodge-recognized-as-asean-green-hotel-2026/
A61: Topas Ecolodge | B61: Current | C61: Waste & Plastic | D61: Food-waste reuse & glass crushing | E61: Food waste được chuyển cho hộ dân/nông dân địa phương; chai thủy tinh được nghiền để tái sử dụng như vật liệu/cát trong công trình. | F61: Core | I61: C – Doanh nghiệp công bố định tính | J61: No – Back-of-house | K61: Practice | L61: Có tuần hoàn link giữa khu nghỉ dưỡng và cộng đồng, nhưng thiếu tỷ lệ chuyển hướng chất thải. | M61: Integration; Community; Evidence & Transparency | N61: F&B / Engineering / Community | O61: Tích hợp liên phòng ban | P61: Topas Sustainable Development | Q61: https://topasecolodge.com/sustainable-development/
A62: Topas Ecolodge | B62: 2026 | C62: Waste & Plastic | D62: Single-use plastic elimination | E62: Topas reports eliminating single-use plastics, replacing them with self-degradable rice-flour bags, reusable bamboo straws and drinking water in glass bottles. | F62: Core | I62: C – Doanh nghiệp công bố định tính | J62: Yes – Visible | K62: Practice | L62: Có mô tả khá rộng về thực hành hiện tại; chưa có KPI tổng khối lượng nhựa hoặc số chai giảm được trên trang. | M62: Integration; Guest Experience; Evidence & Transparency | N62: Rooms / F&B / Housekeeping / Procurement | O62: Tích hợp liên phòng ban | P62: Topas Ecolodge – ASEAN Green Hotel 2026 page | Q62: https://topasecolodge.com/topas-ecolodge-recognized-as-asean-green-hotel-2026/
A63: Topas Ecolodge | B63: Current | C63: Food & Procurement | D63: Local food sourcing & nearby farmers | E63: Topas Ecolodge's 2026 ASEAN Green Hotel disclosure states more than 80% of food and restaurant supplies are purchased directly from local farms in Ban Ho, Nam Cang and Thanh Kim. | F63: Core | G63: 80 | H63: % food & restaurant supplies sourced locally (>) | I63: B – Doanh nghiệp công bố định lượng | J63: Yes – Visible / experience-linked | K63: Output | L63: Thông tin mới hơn và rộng hơn ví dụ cũ về '3 nông hộ trong bán kính 15 km'. Tuy nhiên đây vẫn là số liệu doanh nghiệp tự công bố và chưa có mẫu số theo giá trị mua hàng/phương pháp kiểm toán. | M63: Community; Integration; Evidence & Transparency | N63: F&B / Procurement / Community | O63: Tích hợp liên phòng ban | P63: Topas Ecolodge – ASEAN Green Hotel 2026 page | Q63: https://topasecolodge.com/topas-ecolodge-recognized-as-asean-green-hotel-2026/
A64: Topas Ecolodge | B64: Current review | C64: Biodiversity & Ecosystems | D64: Biodiversity outcome disclosure | E64: Nguồn rà soát cho thấy resort nằm trong landscape Hoàng Liên và có nhiều practice bảo vệ môi trường, nhưng chưa tìm thấy biodiversity outcome KPI cụ thể. | F64: Data gap | I64: E – Chưa tìm thấy minh chứng cụ thể | J64: No – Research-facing | K64: Data gap | L64: Nguồn rà soát cho thấy khu nghỉ dưỡng nằm trong cảnh quan Hoàng Liên và có nhiều hoạt động bảo vệ môi trường, nhưng chưa tìm thấy KPI kết quả đa dạng sinh học cụ thể. | M64: Evidence & Transparency | N64: Sustainability / Environment | O64: Tích hợp ở hệ thống quản lý | Q64: https://topasecolodge.com/sustainable-tourism/
A65: Topas Ecolodge | B65: 2026 | C65: Community & People | D65: Local workforce from neighboring ethnic communities | E65: Topas Ecolodge's 2026 award disclosure states more than 98% of staff are ethnic minorities from surrounding villages; an older sustainability page states about 90%. | F65: Core | G65: 98 | H65: % staff local ethnic minorities (>) | I65: B – Doanh nghiệp công bố định lượng | J65: No – Staff-facing | K65: Output | L65: Sử dụng số liệu công bố mới nhất năm 2026; các trang chính thức cũ hơn nêu khoảng 90%, nên có thể khác thời điểm hoặc cách định nghĩa. | M65: Community; Breadth; Evidence & Transparency | N65: HR / Community | O65: Tích hợp với cộng đồng | P65: Topas Ecolodge – ASEAN Green Hotel 2026 page | Q65: https://topasecolodge.com/topas-ecolodge-recognized-as-asean-green-hotel-2026/
A66: Topas Ecolodge | B66: Current | C66: Culture & Heritage | D66: Local artisans, crafts & cultural identity | E66: Topas sử dụng local artisans/crafts và mô tả việc hỗ trợ thu nhập cho nghệ nhân; kiến trúc/ẩm thực/trải nghiệm gắn với văn hóa địa phương. | F66: Core | I66: C – Doanh nghiệp công bố định tính | J66: Yes – Experience-integrated | K66: Practice | L66: Culture gắn cả thu mua/cộng đồng và trải nghiệm khách; chưa có kết quả bảo tồn định lượng. | M66: Breadth; Community; Guest Experience | N66: Culture / Procurement / Experience / Community | O66: Tích hợp vào trải nghiệm khách | P66: Topas Sustainable Development | Q66: https://topasecolodge.com/sustainable-development/
A67: Topas Ecolodge | B67: Current | C67: Guest Engagement | D67: Cultural workshops & eco-token | E67: Guest có thể tham gia hoạt động văn hóa; resort cũng mô tả eco-token/incentive khi khách bỏ housekeeping để giảm resource use. | F67: Core | I67: C – Doanh nghiệp công bố định tính | J67: Yes – Participatory | K67: Practice | L67: khách được tham gia vào phát triển bền vững/culture thay vì chỉ nhận truyền thông thụ động. | M67: Guest Experience; Integration | N67: Experience / Housekeeping / Culture | O67: Tích hợp vào trải nghiệm khách | P67: Topas Sustainable Development | Q67: https://topasecolodge.com/sustainable-development/
A68: Topas Ecolodge | B68: 2026 | C68: Guest Engagement | D68: Green Leaf Initiative / valley clean-up participation | E68: Topas states it organizes valley-area trash collection and encourages guests to join Green Leaf Initiative activities to protect the Hoang Lien Son landscape. | F68: Supporting | I68: C – Doanh nghiệp công bố định tính | J68: Yes – Participatory | K68: Practice | L68: Hoạt động phát triển bền vững dành cho khách hiện tại; chưa tìm thấy số lượt tham gia công khai. | M68: Guest Experience; Community; Integration | N68: Experience / Sustainability / Community | O68: Tích hợp với khách / điểm đến | P68: Topas Ecolodge – ASEAN Green Hotel 2026 page | Q68: https://topasecolodge.com/topas-ecolodge-recognized-as-asean-green-hotel-2026/
A69: The Westin Resort & Spa Cam Ranh | B69: 2025–2026 | C69: Energy & Climate | D69: 10% reduction target / 3% progress | E69: Sustainability in Action đặt mục tiêu giảm 10% emissions liên quan energy/water/waste vào cuối 2026; tài liệu cho biết đến 31/12/2025 đạt 3% reduction. | F69: Core | G69: 3 | H69: % reduction achieved | I69: B – Doanh nghiệp công bố định lượng | J69: No – Back-of-house | K69: Outcome indicator | L69: Cần giữ đúng phạm vi của tài liệu; không suy ra 3% chỉ từ năng lượng. | M69: Evidence & Transparency; Integration | N69: Engineering / Sustainability / Operations | O69: Tích hợp liên phòng ban | P69: Marriott Sustainability in Action | Q69: https://www.marriott.com/content/dam/marriott-digital/wi/apec/hws/c/cxrwi/en_us/document/assets/wi-cxrwi-sustainability-in-action-12187.pdf
A70: The Westin Resort & Spa Cam Ranh | B70: Current | C70: Energy & Climate | D70: Carbon footprint per room night | E70: Marriott property overview công bố carbon footprint của resort ở mức 83,50 kg CO2e trên mỗi room night. | F70: Core | G70: 83.5 | H70: kg CO2e / room night | I70: B – Doanh nghiệp công bố định lượng | J70: No – Back-of-house | K70: Outcome indicator | L70: KPI cường độ giúp theo dõi hiệu suất tốt hơn; số liệu vẫn do doanh nghiệp tự công bố. | M70: Evidence & Transparency | N70: Engineering / Sustainability | O70: Tích hợp vào vận hành | P70: Trang tổng quan khu nghỉ dưỡng trên Marriott | Q70: https://www.marriott.com/en-us/hotels/cxrwi-the-westin-resort-and-spa-cam-ranh/overview/
A71: The Westin Resort & Spa Cam Ranh | B71: Current | C71: Water | D71: Water footprint per room night | E71: Marriott property overview công bố water footprint 4.539,37 lít trên mỗi room night. | F71: Core | G71: 4539.37 | H71: liters / room night | I71: B – Doanh nghiệp công bố định lượng | J71: No – Back-of-house | K71: Outcome indicator | L71: Đây là một trong số ít chỉ số cường độ trong mẫu nghiên cứu; vẫn là số liệu doanh nghiệp tự công bố. | M71: Evidence & Transparency | N71: Engineering / Sustainability | O71: Tích hợp vào vận hành | P71: Trang tổng quan khu nghỉ dưỡng trên Marriott | Q71: https://www.marriott.com/en-us/hotels/cxrwi-the-westin-resort-and-spa-cam-ranh/overview/
A72: The Westin Resort & Spa Cam Ranh | B72: 2025 | C72: Waste & Plastic | D72: Reusable glass bottles | E72: Từ tháng 1/2025, resort công bố đã tránh hơn 81.000 chai nước nhựa nhờ chuyển sang reusable glass bottles. | F72: Core | G72: 81000 | H72: plastic bottles avoided (>) | I72: B – Doanh nghiệp công bố định lượng | J72: Yes – Visible | K72: Output | L72: Dành cho khách chất thải initiative có chỉ số rõ. | M72: Guest Experience; Evidence & Transparency; Integration | N72: Rooms / F&B / Sustainability | O72: Tích hợp liên phòng ban | P72: Trang Trải nghiệm / phát triển bền vững của khu nghỉ dưỡng trên Marriott | Q72: https://www.marriott.com/en-us/hotels/cxrwi-the-westin-resort-and-spa-cam-ranh/experiences/
A73: The Westin Resort & Spa Cam Ranh | B73: Current | C73: Waste & Plastic | D73: Guest-room recycling | E73: Marriott property overview liệt kê guest-room recycling như một sustainability feature. | F73: Supporting | I73: C – Doanh nghiệp công bố định tính | J73: Yes – Visible | K73: Practice | L73: thực hành được công bố nhưng không có tỷ lệ chuyển hướng/tái chế. | M73: Guest Experience; Evidence & Transparency | N73: Housekeeping / Rooms | O73: Tích hợp vào vận hành | P73: Trang tổng quan khu nghỉ dưỡng trên Marriott | Q73: https://www.marriott.com/en-us/hotels/cxrwi-the-westin-resort-and-spa-cam-ranh/overview/
A74: The Westin Resort & Spa Cam Ranh | B74: Current | C74: Food & Procurement | D74: Responsible protein / seafood sourcing | E74: The property states it prioritizes responsibly raised/caught proteins, avoids vulnerable species and prioritizes sustainable seafood, but publishes no sourcing percentage. | F74: Supporting | I74: C – Doanh nghiệp công bố định tính | J74: Yes – Visible / experience-linked | K74: Practice | L74: Thực hành thu mua có trách nhiệm được mô tả cụ thể nhưng chưa được định lượng ở cấp khu nghỉ dưỡng. | M74: Breadth; Evidence & Transparency | N74: F&B / Procurement | O74: Tích hợp vào vận hành | P74: Trang Trải nghiệm của khu nghỉ dưỡng trên Marriott | Q74: https://www.marriott.com/vi/hotels/cxrwi-the-westin-resort-and-spa-cam-ranh/experiences/
A75: The Westin Resort & Spa Cam Ranh | B75: 2025–2026 | C75: Biodiversity & Ecosystems | D75: Biodiversity protection commitment | E75: The resort's Sustainability in Action statement includes a commitment to protecting and supporting biodiversity, but no property-specific biodiversity species/habitat KPI is disclosed. | F75: Supporting | I75: C – Doanh nghiệp công bố định tính | J75: No – Back-of-house | K75: Commitment | L75: Dùng để cho thấy phạm vi cam kết; không diễn giải thành hiệu suất đa dạng sinh học đã được đo lường. | M75: Breadth; Evidence & Transparency | N75: Sustainability / Landscaping / Operations | O75: Tích hợp ở hệ thống quản lý | P75: Marriott Sustainability in Action | Q75: https://www.marriott.com/content/dam/marriott-digital/wi/apec/hws/c/cxrwi/en_us/document/assets/wi-cxrwi-sustainability-in-action-12187.pdf
A76: The Westin Resort & Spa Cam Ranh | B76: 2025–2026 | C76: Community & People | D76: Road to Give fundraising / school scholarship support | E76: The resort reports achieving its 2025 USD 1,000 Road to Give fundraising target for Operation Smile Vietnam; for 2026 it set a USD 2,000 goal for scholarships at Son Tan Primary School. | F76: Core | G76: 1000 | H76: USD raised in 2025 | I76: B – Doanh nghiệp công bố định lượng | J76: Yes – Community participation | K76: Output | L76: Có đầu ra xã hội cụ thể và mục tiêu tương lai, nhưng chưa chứng minh tác động dài hạn với người hưởng lợi. | M76: Community; Guest Experience; Evidence & Transparency | N76: HR / Community / Front Office / Associates | O76: Tích hợp với cộng đồng | P76: Marriott Sustainability in Action / property overview | Q76: https://www.marriott.com/content/dam/marriott-digital/wi/apec/hws/c/cxrwi/en_us/document/assets/wi-cxrwi-sustainability-in-action-12187.pdf
A77: The Westin Resort & Spa Cam Ranh | B77: Current | C77: Culture & Heritage | D77: Local-material / fishing-village design references | E77: Property overview mô tả thiết kế dùng vật liệu tự nhiên, green roofs và brick screens gợi liên hệ tới nghề/khung cảnh địa phương. | F77: Supporting | I77: C – Doanh nghiệp công bố định tính | J77: Yes – Visible | K77: Practice | L77: Cultural/thiết kế interpretation, không phải heritage bảo tồn kết quả. | M77: Breadth; Guest Experience | N77: Design / Guest Experience | O77: Tích hợp vào trải nghiệm khách | P77: Trang tổng quan khu nghỉ dưỡng trên Marriott | Q77: https://www.marriott.com/en-us/hotels/cxrwi-the-westin-resort-and-spa-cam-ranh/overview/
A78: The Westin Resort & Spa Cam Ranh | B78: 2025–2026 | C78: Guest Engagement | D78: Guest conservation reminders / participation in fundraising | E78: The resort asks guests and visitors to follow water, energy and waste-reduction reminders and allows direct guest contributions to community fundraising through the Front Desk. | F78: Supporting | I78: C – Doanh nghiệp công bố định tính | J78: Yes – Visible / participatory | K78: Practice | L78: Có hoạt động gắn kết khách nhưng chưa công bố tỷ lệ/số lượt tham gia. | M78: Guest Experience; Integration; Evidence & Transparency | N78: Front Office / Rooms / Sustainability / Community | O78: Tích hợp vào trải nghiệm khách | P78: Marriott Sustainability in Action | Q78: https://www.marriott.com/content/dam/marriott-digital/wi/apec/hws/c/cxrwi/en_us/document/assets/wi-cxrwi-sustainability-in-action-12187.pdf
A79: Six Senses Con Dao | B79: 2025 | C79: Energy & Climate | D79: Passive design / partial solar energy | E79: Six Senses Con Dao's 2025 Control Union certification announcement describes reclaimed materials, natural ventilation and partial solar power as part of sustainable design and operations. | F79: Supporting | I79: C – Doanh nghiệp công bố định tính | J79: Yes – Visible | K79: Practice | L79: Cho thấy năng lượng/thiết kế được tích hợp vào vận hành, nhưng chưa có KPI hiện tại về cường độ năng lượng hoặc sản lượng điện mặt trời ở cấp khu nghỉ dưỡng. | M79: Integration; Evidence & Transparency | N79: Design / Engineering / Sustainability | O79: Tích hợp liên phòng ban | P79: Six Senses Con Dao certification announcement | Q79: https://www.sixsensescondao.com/six-senses-con-dao-achieves-prestigious-certification-by-control-union-a-gstc-accredited-certification-body/
A80: Six Senses Con Dao | B80: Current | C80: Water | D80: Treated wastewater for irrigation | E80: Property mô tả sử dụng treated wastewater để tưới khu vườn/landscape. | F80: Supporting | I80: C – Doanh nghiệp công bố định tính | J80: No – Back-of-house | K80: Practice | L80: Tuần hoàn nước trong vận hành; chưa có tổng lượng/tỷ lệ tái sử dụng. | M80: Integration; Evidence & Transparency | N80: Engineering / Landscaping / Sustainability | O80: Tích hợp liên phòng ban | P80: Trang phát triển bền vững chính thức của khu nghỉ dưỡng | Q80: https://www.sixsenses.com/en/hotels-resorts/asia-the-pacific/vietnam/con-dao/sustainability/
A81: Six Senses Con Dao | B81: 2025 | C81: Waste & Plastic | D81: Single-use plastic bottles avoided | E81: Property công bố 97.656 chai nhựa dùng một lần được tránh trong năm 2025. | F81: Core | G81: 97656 | H81: plastic bottles avoided | I81: B – Doanh nghiệp công bố định lượng | J81: Yes – Visible | K81: Output | L81: Đây là đầu ra chất thải có số liệu cụ thể, nhưng chưa phản ánh tổng lượng nhựa của khu nghỉ dưỡng. | M81: Evidence & Transparency; Integration | N81: Rooms / F&B / Sustainability | O81: Tích hợp liên phòng ban | P81: Trang phát triển bền vững chính thức của khu nghỉ dưỡng | Q81: https://www.sixsenses.com/en/hotels-resorts/asia-the-pacific/vietnam/con-dao/sustainability/
A82: Six Senses Con Dao | B82: 2025 | C82: Waste & Plastic | D82: 2R Station plastic diversion | E82: In collaboration with WWF and the Con Dao Youth Union, the 2R Station diverted 305 kg of plastic waste from landfill in 2025. | F82: Supporting | G82: 305 | H82: kg plastic diverted | I82: B – Doanh nghiệp công bố định lượng | J82: No – Community/destination-facing | K82: Output | L82: Có nêu rõ đối tác, nhưng con số vẫn lấy từ công bố của Six Senses nếu chưa có nguồn riêng đối chiếu. | M82: Community; Waste; Evidence & Transparency | N82: Sustainability / Community / External partners | O82: Tích hợp với cộng đồng | P82: Trang phát triển bền vững chính thức của khu nghỉ dưỡng | Q82: https://www.sixsenses.com/en/hotels-resorts/asia-the-pacific/vietnam/con-dao/sustainability/
A83: Six Senses Con Dao | B83: 2025 | C83: Waste & Plastic | D83: National Park beach clean-ups | E83: Property công bố 1.763 kg rác được thu gom từ các bãi biển thuộc National Park trong 2025. | F83: Supporting | G83: 1763 | H83: kg trash collected | I83: B – Doanh nghiệp công bố định lượng | J83: Mixed | K83: Output | L83: cộng đồng/điểm đến hoạt động về chất thải; không phải khu nghỉ dưỡng chất thải-chuyển hướng KPI. | M83: Community; Biodiversity; Evidence & Transparency | N83: Sustainability / Community / National Park | O83: Tích hợp với cộng đồng | P83: Trang phát triển bền vững chính thức của khu nghỉ dưỡng | Q83: https://www.sixsenses.com/en/hotels-resorts/asia-the-pacific/vietnam/con-dao/sustainability/
A84: Six Senses Con Dao | B84: 2025 | C84: Food & Procurement | D84: Organic garden production | E84: Khu vườn hữu cơ khoảng 3.000 m² cùng các hoạt động trồng trọt/chăn nuôi tại property; resort công bố 5.641,70 kg rau tươi thu hoạch trong 2025. | F84: Core | G84: 5641.7 | H84: kg fresh vegetables | I84: B – Doanh nghiệp công bố định lượng | J84: Yes – Visible / experience-linked | K84: Output | L84: Onsite sản xuất minh chứng; chưa có % tổng F&B demand được đáp ứng. | M84: Integration; Guest Experience; Evidence & Transparency | N84: F&B / Sustainability / Procurement | O84: Tích hợp liên phòng ban | P84: Trang phát triển bền vững chính thức của khu nghỉ dưỡng | Q84: https://www.sixsenses.com/en/hotels-resorts/asia-the-pacific/vietnam/con-dao/sustainability/
A85: Six Senses Con Dao | B85: 2025 | C85: Biodiversity & Ecosystems | D85: Green sea turtle conservation | E85: Six Senses Con Dao công bố 3.818 rùa xanh nguy cấp nở và được thả về biển trong năm 2025, phối hợp với Con Dao National Park. | F85: Core | G85: 3818 | H85: turtles hatched/released | I85: B – Doanh nghiệp công bố định lượng | J85: Yes – Participatory | K85: Output | L85: Đầu ra bảo tồn khá rõ, nhưng không nên tự suy ra tác động dài hạn tới quần thể. | M85: Guest Experience; Biodiversity; Evidence & Transparency | N85: Sustainability / National Park / Experience | O85: Tích hợp với khách / điểm đến | P85: Trang phát triển bền vững chính thức của khu nghỉ dưỡng | Q85: https://www.sixsenses.com/en/hotels-resorts/asia-the-pacific/vietnam/con-dao/sustainability/
A86: Six Senses Con Dao | B86: 2024–2025 | C86: Community & People | D86: Water for All | E86: Property mô tả chương trình Water for All với 12 máy lọc nước và 3.879 người trong cộng đồng được hưởng lợi. | F86: Core | G86: 3879 | H86: community beneficiaries | I86: B – Doanh nghiệp công bố định lượng | J86: No – Community-facing | K86: Output | L86: Có chỉ số đầu ra xã hội rõ, nhưng chưa nên diễn giải thành kết quả sức khỏe dài hạn. | M86: Community; Evidence & Transparency | N86: Community / Sustainability / Water | O86: Tích hợp với cộng đồng | P86: Trang phát triển bền vững chính thức của khu nghỉ dưỡng | Q86: https://www.sixsenses.com/en/hotels-resorts/asia-the-pacific/vietnam/con-dao/sustainability/
A87: Six Senses Con Dao | B87: 2025 | C87: Community & People | D87: English education | E87: Property công bố 84 giờ English classes cho cộng đồng trong năm 2025. | F87: Supporting | G87: 84 | H87: hours | I87: B – Doanh nghiệp công bố định lượng | J87: No – Community-facing | K87: Output | L87: Trang tiếng Anh báo cáo 84 giờ năm 2025; tiêu đề trang tiếng Việt cũng ghi 84 giờ nhưng phần nội dung chi tiết lại ghi 94 giờ. Giữ 84 giờ vì nhất quán giữa tiêu đề và trang tiếng Anh, đồng thời ghi nhận chênh lệch nội bộ của nguồn. | M87: Community; Evidence & Transparency | N87: Community / Learning & Development | O87: Tích hợp với cộng đồng | P87: Trang phát triển bền vững chính thức của khu nghỉ dưỡng | Q87: https://www.sixsenses.com/en/hotels-resorts/asia-the-pacific/vietnam/con-dao/sustainability/
A88: Six Senses Con Dao | B88: Current | C88: Culture & Heritage | D88: Fishing-village design identity | E88: Property mô tả thiết kế lấy cảm hứng từ/giữ tinh thần của làng chài Côn Đảo trong kiến trúc resort. | F88: Supporting | I88: C – Doanh nghiệp công bố định tính | J88: Yes – Visible | K88: Practice | L88: Cultural interpretation through thiết kế; chưa phải heritage kết quả. | M88: Breadth; Guest Experience | N88: Design / Culture / Experience | O88: Tích hợp vào trải nghiệm khách | P88: Trang chính thức của Six Senses | Q88: https://www.sixsenses.com/en/hotels-resorts/asia-the-pacific/vietnam/con-dao/sustainability/
A89: Six Senses Con Dao | B89: Current | C89: Guest Engagement | D89: Turtle hatching / release experience | E89: Khách được mời tìm hiểu và tham gia trải nghiệm thả rùa khi điều kiện/timing phù hợp, gắn conservation trực tiếp với guest journey. | F89: Core | I89: C – Doanh nghiệp công bố định tính | J89: Yes – Participatory | K89: Practice | L89: Một case rõ về bảo tồn trở thành hospitality experience. | M89: Guest Experience; Integration; Biodiversity | N89: Experience / Sustainability / National Park | O89: Tích hợp vào trải nghiệm khách | P89: Trang phát triển bền vững chính thức của khu nghỉ dưỡng | Q89: https://www.sixsenses.com/en/hotels-resorts/asia-the-pacific/vietnam/con-dao/sustainability/
A90: Six Senses Con Dao | B90: Current | C90: Guest Engagement | D90: Earth Lab / Green Journey / garden learning | E90: Property sustainability and experience pages invite guests to Earth Lab, sustainability tours and garden-based learning/harvesting experiences. | F90: Supporting | I90: C – Doanh nghiệp công bố định tính | J90: Yes – Participatory | K90: Practice | L90: Cho thấy phát triển bền vững được tích hợp rộng hơn bảo tồn rùa; chưa tìm thấy KPI tổng hợp về lượt khách tham gia. | M90: Guest Experience; Integration | N90: Experience / F&B / Sustainability | O90: Tích hợp vào trải nghiệm khách | P90: Các trang chính thức của Six Senses Con Dao | Q90: https://www.sixsenses.com/en/hotels-resorts/asia-the-pacific/vietnam/con-dao/sustainability/
A91: Mango Bay Phu Quoc | B91: Current | C91: Energy & Climate | D91: Natural ventilation / solar hot water / low-energy design | E91: Mango Bay mô tả ưu tiên thông gió tự nhiên, solar hot water, natural light và các thiết bị/đèn tiết kiệm năng lượng để giảm nhu cầu điện. | F91: Core | I91: C – Doanh nghiệp công bố định tính | J91: Yes – Visible | K91: Practice | L91: thiết kế-led năng lượng sttỷ lệgy, nhưng chưa thấy cường độ sử dụng năng lượng/carbon KPI. | M91: Integration; Guest Experience; Evidence & Transparency | N91: Design / Engineering / Rooms | O91: Tích hợp liên phòng ban | P91: Trang Giới thiệu / Staying Green chính thức của Mango Bay | Q91: https://mangobayphuquoc.com/en/about/
A92: Mango Bay Phu Quoc | B92: Current | C92: Water | D92: On-site water / wastewater treatment practices | E92: Mango Bay describes low-flow toilets, reed-bed greywater filtration and reuse of treated water for gardens/tree nurseries, alongside septic/wastewater management. | F92: Supporting | I92: C – Doanh nghiệp công bố định tính | J92: No – Back-of-house | K92: Practice | L92: Có mô tả cụ thể cách xử lý/tái sử dụng nước, nhưng chưa công bố tổng lượng nước hằng năm hoặc cường độ sử dụng nước. | M92: Integration; Evidence & Transparency | N92: Engineering / Sustainability | O92: Tích hợp vào vận hành | P92: Trang Giới thiệu / Staying Green chính thức của Mango Bay | Q92: https://mangobayphuquoc.com/en/about/
A93: Mango Bay Phu Quoc | B93: Current | C93: Waste & Plastic | D93: Bulk buying, recycling & organic-waste reuse | E93: Resort mô tả mua hàng bulk để giảm packaging, tái chế paper/glass và đưa organic/food waste cho vật nuôi hoặc mục đích tái sử dụng. | F93: Core | I93: C – Doanh nghiệp công bố định tính | J93: No – Back-of-house | K93: Practice | L93: Chất thải tuần hoàn thực hành nhưng thiếu chất thải chuyển hướng KPI. | M93: Integration; Evidence & Transparency | N93: Procurement / F&B / Housekeeping | O93: Tích hợp liên phòng ban | P93: Trang Giới thiệu / Staying Green chính thức của Mango Bay | Q93: https://mangobayphuquoc.com/en/about/
A94: Mango Bay Phu Quoc | B94: Current | C94: Food & Procurement | D94: Local purchasing | E94: Mango Bay công bố hơn 85% purchasing đến từ local suppliers. | F94: Core | G94: 85 | H94: % purchasing local suppliers (>) | I94: B – Doanh nghiệp công bố định lượng | J94: Yes – Visible / experience-linked | K94: Output | L94: Một quantified thu mua chỉ số mạnh; cần giữ đúng cách định nghĩa purchasing của khu nghỉ dưỡng. | M94: Community; Integration; Evidence & Transparency | N94: Procurement / F&B / Community | O94: Tích hợp liên phòng ban | P94: Trang Giới thiệu / Staying Green chính thức của Mango Bay | Q94: https://mangobayphuquoc.com/en/about/
A95: Mango Bay Phu Quoc | B95: Historical / ongoing programme | C95: Biodiversity & Ecosystems | D95: Wildlife At Risk biodiversity surveys | E95: Wildlife At Risk mô tả các khảo sát đa dạng sinh học tại Phú Quốc và hoạt động có liên quan Mango Bay, gồm survey butterflies/dragonflies và pilot butterfly breeding. | F95: Core | I95: D – Xác nhận từ đối tác bên ngoài | J95: No – Research-facing | K95: Practice | L95: đối tác source giúp giảm phụ thuộc vào khu nghỉ dưỡng self-report; không coi survey counts là kết quả của khu nghỉ dưỡng. | M95: Evidence & Transparency; Biodiversity | N95: Sustainability / Conservation partner | O95: Tích hợp nghiên cứu / bảo tồn | P95: Wildlife At Risk – Phu Quoc Programme | Q95: https://wildlifeatrisk.org/2019/01/29/phu-quoc-programme/
A96: Mango Bay Phu Quoc | B96: Since 2006 / historical partner evidence | C96: Biodiversity & Ecosystems | D96: Native species restoration with WAR / Phu Quoc National Park | E96: Mango Bay states it supports Wildlife At Risk and Phu Quoc National Park to collect and replant Dipterocarpus, a native plant becoming rare on the island. | F96: Supporting | I96: C – Doanh nghiệp công bố định tính | J96: No – Conservation-facing | K96: Practice | L96: Hoạt động bảo tồn kéo dài nhiều năm; chưa tìm thấy KPI về tỷ lệ sống hoặc kết quả sinh cảnh. | M96: Biodiversity; Community; Evidence & Transparency | N96: Sustainability / External partner / National Park | O96: Tích hợp nghiên cứu / bảo tồn | P96: Trang Giới thiệu chính thức của Mango Bay | Q96: https://mangobayphuquoc.com/en/about/
A97: Mango Bay Phu Quoc | B97: Current | C97: Community & People | D97: Local employment | E97: Mango Bay công bố hơn 80% nhân sự là người địa phương, cùng các hoạt động training/support cho staff. | F97: Core | G97: 80 | H97: % staff local (>) | I97: B – Doanh nghiệp công bố định lượng | J97: No – Staff-facing | K97: Output | L97: Có chỉ số xã hội/con người rõ; dữ liệu do doanh nghiệp tự công bố. | M97: Community; Breadth; Evidence & Transparency | N97: HR / Community | O97: Tích hợp với cộng đồng | P97: Trang Giới thiệu / Staying Green chính thức của Mango Bay | Q97: https://mangobayphuquoc.com/en/about/
A98: Mango Bay Phu Quoc | B98: Current | C98: Culture & Heritage | D98: Local craftsmen & materials | E98: Mango Bay mô tả sử dụng local craftsmen và local/recycled materials trong xây dựng/vận hành để phản ánh bối cảnh Phú Quốc. | F98: Supporting | I98: C – Doanh nghiệp công bố định tính | J98: Yes – Visible | K98: Practice | L98: Có tích hợp yếu tố văn hóa/địa phương, nhưng chưa có chỉ số kết quả về bảo tồn di sản. | M98: Breadth; Guest Experience | N98: Design / Procurement / Community | O98: Tích hợp vào trải nghiệm khách | P98: Trang Giới thiệu / Staying Green chính thức của Mango Bay | Q98: https://mangobayphuquoc.com/en/about/
A99: Mango Bay Phu Quoc | B99: Current review | C99: Guest Engagement | D99: Structured sustainability participation metrics | E99: Trong nguồn rà soát, chưa tìm thấy metric hiện hành về số guest tham gia hoạt động sustainability/conservation tại Mango Bay. | F99: Data gap | I99: E – Chưa tìm thấy minh chứng cụ thể | J99: Yes – Visible | K99: Data gap | L99: khu nghỉ dưỡng có eco-thiết kế/nature positioning nhưng công bố khách-sự tham gia chưa cụ thể. | M99: Guest Experience; Evidence & Transparency | N99: Experience / Sustainability | O99: Tích hợp vào trải nghiệm khách | Q99: https://mangobayphuquoc.com/en/about/
A100: Mango Bay Phu Quoc | B100: 2015 (historical) | C100: Guest Engagement | D100: Wildlife awareness photo exhibition with WAR | E100: Wildlife At Risk reports a month-long 'Lucky Wildlife' photo exhibition at Mango Bay in 2015; roughly 40 people attended the opening and more than 40 endangered-wildlife photos were displayed. | F100: Appendix | G100: 40 | H100: opening attendees (approx.) | I100: D – Xác nhận từ đối tác bên ngoài | J100: Yes – Participatory / educational | K100: Output | L100: Bằng chứng lịch sử về giáo dục khách/công chúng; hữu ích để xem tính tiếp nối nhưng không phải KPI tham gia hiện tại. | M100: Guest Experience; Biodiversity; Evidence & Transparency | N100: Experience / Conservation partner | O100: Tích hợp với khách / điểm đến | P100: Wildlife At Risk | Q100: https://wildlifeatrisk.org/activities/lastest-news/
...

Sheet Quản lý & Tích hợp
A1: Khu nghỉ dưỡng | B1: Phạm vi | C1: Năm | D1: Management / Integration Practice | E1: Thông tin lọc được | F1: Keep? | G1: Metric | H1: Unit | I1: Evidence Type | J1: Nguồn từ | K1: Evidence Stage | L1: Mức độ tích hợp | M1: Ghi chú | N1: Source Link
A2: Six Senses Ninh Van Bay | B2: Cấp khu nghỉ dưỡng | C2: 2024–2027 | D2: Chứng nhận theo tiêu chuẩn được GSTC công nhận | E2: Six Senses Ninh Van Bay có tên trong Danh bạ Khách sạn được chứng nhận GSTC; Tổ chức chứng nhận: Control Union (GSTC-I); mã chứng nhận GSTC HACU240332-12; chu kỳ 30/12/2024–29/12/2027. | F2: Cốt lõi | I2: A – Xác minh độc lập | J2: GSTC Certified Hotels Directory | K2: Xác minh | L2: Tích hợp ở hệ thống quản lý | M2: Bằng chứng độc lập về trạng thái chứng nhận; không dùng để nói từng KPI của khu nghỉ dưỡng đã được GSTC kiểm toán công khai. | N2: https://www.gstc.org/certified-hotels-directory/
A3: Six Senses Ninh Van Bay | B3: Thương hiệu → khu nghỉ dưỡng | C3: Hiện tại | D3: Regenerative Impact Fund | E3: Six Senses quy định mỗi khu nghỉ dưỡng quản lý Regenerative Impact Fund, gồm 0,5% tổng doanh thu khách sạn cùng nguồn thu từ bán mascot/quyên góp để đầu tư vào các dự án cộng đồng, sinh cảnh và động vật hoang dã tại địa phương. | F3: Cốt lõi | G3: 0.5 | H3: % tổng doanh thu | I3: B – Doanh nghiệp công bố định lượng | J3: Six Senses brand sustainability / impacts | K3: Thực hành | L3: Tích hợp liên phòng ban | M3: Cho thấy phát triển bền vững được gắn với cơ chế nguồn tài chính ở cấp khu nghỉ dưỡng; chưa thấy số tiền tuyệt đối riêng của Ninh Van Bay. | N3: https://www.sixsenses.com/en/sustainability/impacts/
A4: Six Senses Ninh Van Bay | B4: Thương hiệu → khu nghỉ dưỡng | C4: Hiện tại | D4: Climate Action Plan / phạm vi liên phòng ban | E4: Six Senses mô tả quản lý khí hậu/phát triển bền vững bao quát vận hành, chất thải và tuần hoàn, đa dạng sinh học, nước, nhà cung cấp, khách và nhân viên. | F4: Bổ trợ | I4: C – Doanh nghiệp công bố định tính | J4: Six Senses brand impacts page | K4: Cam kết | L4: Tích hợp liên phòng ban | M4: Cho thấy phát triển bền vững được mô tả theo hướng liên phòng ban ở cấp thương hiệu; chưa phải kết quả ở cấp khu nghỉ dưỡng. | N4: https://www.sixsenses.com/en/sustainability/impacts/
A5: Six Senses Ninh Van Bay | B5: Thương hiệu → khu nghỉ dưỡng | C5: 2025 | D5: Vị trí Sustainability Director chuyên trách | E5: Six Senses công bố Sustainability Directors tại các khách sạn để dẫn dắt hoạt động tạo tác động tích cực của từng khu nghỉ dưỡng; Earth Labs hỗ trợ gắn kết và đổi mới. | F5: Bổ trợ | I5: C – Doanh nghiệp công bố định tính | J5: Six Senses corporate press release | K5: Thực hành | L5: Tích hợp ở hệ thống quản lý | M5: Bổ sung bằng chứng về cấu trúc quản trị/vai trò phụ trách phát triển bền vững; nguồn là doanh nghiệp tự công bố. | N5: https://www.sixsenses.com/en/corporate/media-center/press-releases/2025/control-union-gstc-certification/
A6: Six Senses Ninh Van Bay | B6: Thương hiệu → khu nghỉ dưỡng | C6: Hiện tại | D6: Theo dõi môi trường & đối sánh với Cornell | E6: Six Senses cho biết các khu nghỉ dưỡng theo dõi/đo lường nỗ lực môi trường và toàn bộ khách sạn/khu nghỉ dưỡng đóng góp dữ liệu cho Cornell Hotel Sustainability Benchmarking. | F6: Bổ trợ | I6: C – Doanh nghiệp công bố định tính | J6: Six Senses brand impacts page | K6: Thực hành | L6: Tích hợp ở hệ thống quản lý | M6: Quan trọng cho góc nhìn quản lý; chưa thấy điểm đối sánh công khai riêng của Ninh Van Bay. | N6: https://www.sixsenses.com/en/sustainability/impacts/
A7: Six Senses Ninh Van Bay | B7: Cấp khu nghỉ dưỡng | C7: 2024 | D7: Giải HICAP về Hành động Khí hậu & Đa dạng sinh học | E7: HICAP 2024 Giải thưởng Khách sạn Bền vững công bố Six Senses Ninh Van Bay là đơn vị thắng giải hạng mục Hành động Khí hậu & Đa dạng sinh học. | F7: Bổ trợ | I7: A2 – Ghi nhận độc lập | J7: HICAP / BHN Group | K7: Ghi nhận | L7: Tích hợp ở hệ thống quản lý | M7: Ghi nhận bên ngoài, không tương đương kiểm toán từng KPI phát triển bền vững. | N7: https://www.burba.com/HICAP/News/HICAP-2024-Sustainable-Award-Winners
A8: InterContinental Danang Sun Peninsula Resort | B8: Cấp khu nghỉ dưỡng | C8: Hiện tại | D8: Chứng nhận Green Globe | E8: Green Globe có trang riêng xác nhận InterContinental Danang Sun Peninsula Resort trong chương trình chứng nhận; khu nghỉ dưỡng cũng tự công bố trạng thái Green Globe Certified. | F8: Cốt lõi | I8: A – Xác minh độc lập | J8: Green Globe | K8: Xác minh | L8: Tích hợp ở hệ thống quản lý | M8: Dùng để xác minh chứng nhận trạng thái; không coi chứng nhận là kiểm toán công khai của từng KPI khu nghỉ dưỡng. | N8: https://www.greenglobe.com/news/intercontinental-danang-sun-peninsula-resort
A9: InterContinental Danang Sun Peninsula Resort | B9: Cấp khu nghỉ dưỡng | C9: 2026–2027 | D9: Kế hoạch Quản lý Phát triển bền vững | E9: Khu nghỉ dưỡng công khai Kế hoạch Quản lý Phát triển Bền vững 2026–2027, cấu trúc theo các cam kết về Môi trường, Xã hội – Văn hóa, Chất lượng và Sức khỏe – An toàn, đồng thời mô tả theo dõi/chính sách cho vận hành. | F9: Cốt lõi | I9: C – Doanh nghiệp công bố định tính | J9: Kế hoạch Quản lý Phát triển bền vững của khu nghỉ dưỡng | K9: Thực hành | L9: Tích hợp ở hệ thống quản lý | M9: Minh chứng mạnh về quản lý/tích hợp; phần lớn dữ liệu hiệu suất trong kế hoạch vẫn định tính. | N9: https://www.danang.intercontinental.com/wp-content/uploads/2025/11/SUSTAINABILITY-MANAGEMENT-PLAN-2026-2027.pdf
A10: Banyan Tree Lang Co | B10: Cấp khu nghỉ dưỡng | C10: 2025–2028 | D10: Chứng nhận theo tiêu chuẩn được GSTC công nhận | E10: Danh bạ Khách sạn được chứng nhận GSTC liệt kê Banyan Tree Lang Co; Tổ chức chứng nhận: Control Union (GSTC-I); chu kỳ 16/12/2025–15/12/2028; chứng nhận GSTC HACU250270-1. | F10: Cốt lõi | I10: A – Xác minh độc lập | J10: GSTC Certified Hotels Directory | K10: Xác minh | L10: Tích hợp ở hệ thống quản lý | M10: Bằng chứng chứng nhận độc lập ở cấp khu nghỉ dưỡng; không dùng để xác minh từng KPI khác. | N10: https://www.gstc.org/certified-hotels-directory/
A11: Banyan Tree Lang Co | B11: Cấp khu nghỉ dưỡng | C11: Hiện tại | D11: Green Imperative Fund | E11: Banyan Tree Lang Co mô tả Green Imperative Fund với khoản đóng góp tự động tính nhưng khách có thể từ chối 2 USD mỗi đêm phòng để hỗ trợ các sáng kiến môi trường/cộng đồng. | F11: Cốt lõi | G11: 2 | H11: USD / đêm phòng | I11: B – Doanh nghiệp công bố định lượng | J11: Banyan Tree Lang Co Sustainability | K11: Thực hành | L11: Tích hợp liên phòng ban | M11: Cho thấy cơ chế tài chính gắn với kỳ nghỉ; chưa thấy số liệu phân tách kết quả của riêng khu nghỉ dưỡng trên trang. | N11: https://www.banyantree.com/vietnam/lang-co/sustainability
A12: Banyan Tree Lang Co | B12: Bối cảnh khu phức hợp | C12: 2022 | D12: EarthCheck Gold – Laguna Lăng Cô | E12: EarthCheck công bố Laguna Lăng Cô giữ EarthCheck Gold năm 2022. Đây là lịch sử chứng nhận của khu phức hợp, không phải bằng chứng hiện tại riêng cho Banyan Tree Lang Co. | F12: Bổ trợ | I12: A – Xác minh độc lập | J12: EarthCheck | K12: Xác minh | L12: Tích hợp ở hệ thống quản lý | M12: Giữ như lịch sử/phạm vi context; không dùng để công bố hiện tại Banyan Tree chứng nhận. | N12: https://earthcheck.org/news/laguna-golf-lang-co-retains-earthcheck-gold/
A13: Topas Ecolodge | B13: Cấp khu nghỉ dưỡng | C13: 2026 | D13: Giải Khách sạn Xanh ASEAN 2026 | E13: Nguồn thuộc hệ thống thông tin du lịch Việt Nam công bố Topas Ecolodge là một trong các cơ sở Việt Nam nhận ASEAN Green Hotel Award 2026. | F13: Cốt lõi | I13: A2 – Ghi nhận độc lập | J13: Viet Nam public-sector / national press confirmation | K13: Ghi nhận | L13: Tích hợp ở hệ thống quản lý | M13: Giải thưởng được nguồn công lập/báo chí quốc gia Việt Nam xác nhận; đây là ghi nhận bên ngoài, không tương đương kiểm toán từng KPI của khu nghỉ dưỡng. | N13: https://en.nhandan.vn/viet-nam-reaps-a-bountiful-harvest-at-the-asean-tourism-awards-2026-post158773.html
A14: Topas Ecolodge | B14: Cấp khu nghỉ dưỡng | C14: Hiện tại | D14: Cách tiếp cận quản lý du lịch bền vững / CSR | E14: Topas công khai các nguyên tắc vận hành về địa phương employment, sourcing, energy, nước, chất thải, văn hóa và cộng đồng trên sustainable tourism/development trangs. | F14: Cốt lõi | I14: C – Doanh nghiệp công bố định tính | J14: Topas official sustainability pages | K14: Thực hành | L14: Tích hợp liên phòng ban | M14: Cho thấy phát triển bền vững được mô tả theo hướng liên phòng ban; chưa thấy báo cáo hiệu suất hiện tại với các KPI cường độ. | N14: https://topasecolodge.com/sustainable-development/
A15: The Westin Resort & Spa Cam Ranh | B15: Cấp khu nghỉ dưỡng | C15: 2025–2026 | D15: Mục tiêu & theo dõi tiến độ trong Sustainability in Action | E15: Khu nghỉ dưỡng công bố mục tiêu 10% mức giảm vào cuối 2026 và cập nhật tiến độ 3% đến 31/12/2025 trong Sustainability in Action tài liệu. | F15: Cốt lõi | G15: 10 | H15: % mục tiêu giảm | I15: B – Doanh nghiệp công bố định lượng | J15: Marriott Sustainability in Action | K15: Cam kết | L15: Tích hợp ở hệ thống quản lý | M15: Có mục tiêu + tiến độ công bố; cần giữ đúng indicator phạm vi nêu trong tài liệu. | N15: https://www.marriott.com/content/dam/marriott-digital/wi/apec/hws/c/cxrwi/en_us/document/assets/wi-cxrwi-sustainability-in-action-12187.pdf
A16: The Westin Resort & Spa Cam Ranh | B16: Cấp khu nghỉ dưỡng | C16: Hiện tại | D16: Travelife Certified – doanh nghiệp công bố | E16: Trang tổng quan Marriott hiển thị trạng thái 'Travelife Certified'. Trong đợt rà hiện tại chưa xác minh được hồ sơ này bằng danh bạ công khai gốc của Travelife. | F16: Cốt lõi | I16: C – Doanh nghiệp công bố định tính | J16: Trang tổng quan khu nghỉ dưỡng trên Marriott | K16: Xác minh | L16: Tích hợp ở hệ thống quản lý | M16: Giữ ở mức doanh nghiệp công bố về tình trạng chứng nhận cho tới khi có nguồn trực tiếp từ Travelife. | N16: https://www.marriott.com/en-us/hotels/cxrwi-the-westin-resort-and-spa-cam-ranh/overview/
A17: Six Senses Con Dao | B17: Cấp khu nghỉ dưỡng | C17: 2024–2027 | D17: Chứng nhận theo tiêu chuẩn được GSTC công nhận | E17: Danh bạ Khách sạn được chứng nhận GSTC liệt kê Six Senses Condao; Control Union (GSTC-I); hiện tại chu kỳ 30/12/2024–29/12/2027; chứng nhận GSTC HACU240332-1. | F17: Cốt lõi | I17: A – Xác minh độc lập | J17: GSTC Certified Hotels Directory | K17: Xác minh | L17: Tích hợp ở hệ thống quản lý | M17: hiện tại chứng nhận được xác nhận trong danh bạ at cấp khu nghỉ dưỡng; không dùng chứng nhận này để xác minh từng KPI phát triển bền vững khác. | N17: https://www.gstc.org/certified-hotels-directory/
A18: Six Senses Con Dao | B18: Thương hiệu → khu nghỉ dưỡng | C18: Hiện tại | D18: Cơ chế quỹ tái tạo / phát triển bền vững | E18: Six Senses áp dụng Regenerative Impact Fund tại các khu nghỉ dưỡng, với 0,5% tổng doanh thu khách sạn cùng các nguồn bổ sung dành cho các dự án môi trường và xã hội tại địa phương. | F18: Cốt lõi | G18: 0.5 | H18: % tổng doanh thu khách sạn | I18: B – Doanh nghiệp công bố định lượng | J18: Six Senses Impacts | K18: Thực hành | L18: Tích hợp liên phòng ban | M18: nguồn tài chính architecture cấp brand/khu nghỉ dưỡng; không có absolute fund amount của Con Dao trong source này. | N18: https://www.sixsenses.com/en/sustainability/impacts/
A19: Mango Bay Phu Quoc | B19: Cấp khu nghỉ dưỡng | C19: Hiện tại | D19: Staying Green / nguyên tắc vận hành sinh thái | E19: Mango Bay công khai 'Staying Green' approach bao quát low-energy design, nước/chất thải, địa phương purchasing/employment, địa phương materials và conservation partnerships. | F19: Cốt lõi | I19: C – Doanh nghiệp công bố định tính | J19: Trang Giới thiệu / Staying Green chính thức của Mango Bay | K19: Thực hành | L19: Tích hợp liên phòng ban | M19: Mô tả quản lý liên phòng ban; chưa thấy báo cáo phát triển bền vững hiện tại có chỉ số cường độ được công bố công khai. | N19: https://mangobayphuquoc.com/en/about/
A20: Mango Bay Phu Quoc | B20: Cấp khu nghỉ dưỡng | C20: Rà soát hiện tại | D20: Chứng nhận phát triển bền vững bên thứ ba | E20: Trong các nguồn chính thức/partner đã rà, chưa tìm thấy hiện tại third-party phát triển bền vững chứng nhận công khai cho Mango Bay. | F20: Khoảng trống dữ liệu | I20: E – Chưa tìm thấy minh chứng cụ thể | J20: Rà soát các nguồn đã liệt kê | K20: Khoảng trống dữ liệu | L20: Tích hợp ở hệ thống quản lý | M20: Không đồng nghĩa khu nghỉ dưỡng không có chứng nhận; chỉ phản ánh công khai minh chứng tìm được. | N20: https://mangobayphuquoc.com/en/about/
A21: Avana Retreat | B21: Cấp khu nghỉ dưỡng | C21: Hiện tại | D21: Khung quản lý phát triển bền vững | E21: Avana công khai cách tiếp cận quản lý phát triển bền vững bao quát phục hồi rừng, đa dạng sinh học, cộng đồng/lao động địa phương, văn hóa, thực phẩm và giảm chất thải. | F21: Cốt lõi | I21: C – Doanh nghiệp công bố định tính | J21: Avana Retreat Sustainability | K21: Thực hành | L21: Tích hợp liên phòng ban | M21: Có minh chứng rộng về quản lý/tích hợp; công bố công khai về năng lượng và cường độ sử dụng nước còn hạn chế. | N21: https://avanaretreat.com/sustainability
A22: Avana Retreat | B22: Nền tảng bên ngoài | C22: 2025/hiện tại | D22: Đánh giá đa dạng sinh học của Guardians of Earth | E22: Guardians of Earth có Avana Retreat trên đa dạng sinh học platform và công bố site-level đa dạng sinh học indicators; các snapshot hiện hành có thể khác số khu nghỉ dưỡng trích trong 2025 phát triển bền vững trang. | F22: Bổ trợ | I22: D – Đánh giá/xác nhận từ đối tác bên ngoài | J22: Guardians of Earth – Biocultural Health Report 2025 | K22: Xác minh / đánh giá | L22: Tích hợp nghiên cứu / bảo tồn | M22: Đây là báo cáo/đánh giá sinh học – văn hóa từ đối tác bên ngoài, không phải chứng nhận phát triển bền vững khách sạn. Dùng như nguồn đánh giá/đối chiếu của đối tác, không coi là chứng nhận độc lập. | N22: https://avanaretreat.com/storage/2025/09/Biocultural-Health-Report-Avana-Retreat-2025.pdf
A23: Avana Retreat | B23: Cấp khu nghỉ dưỡng | C23: Rà soát hiện tại | D23: Chứng nhận phát triển bền vững khách sạn bên thứ ba | E23: Trong các nguồn đã rà, chưa xác minh hiện tại hotel phát triển bền vững chứng nhận như GSTC-accredited/Green Globe/Travelife cho Avana. | F23: Khoảng trống dữ liệu | I23: E – Chưa tìm thấy minh chứng cụ thể | J23: Rà soát các nguồn đã liệt kê | K23: Khoảng trống dữ liệu | L23: Tích hợp ở hệ thống quản lý | M23: Guardians of Earth đa dạng sinh học assessment không tương đương hotel phát triển bền vững chứng nhận. | N23: https://avanaretreat.com/sustainability
A24: Silk Sense Hoi An River Resort | B24: Cấp khu nghỉ dưỡng | C24: 2024–2025 | D24: Báo cáo Phát triển Bền vững | E24: Khu nghỉ dưỡng công khai Báo cáo Phát triển Bền vững 2024–2025 bao phủ năng lượng, nước, chất thải, chuỗi cung ứng, cộng đồng, đa dạng sinh học và việc làm/đối xử công bằng. | F24: Cốt lõi | I24: C – Doanh nghiệp công bố định tính | J24: Silk Sense Sustainability Report 2024–2025 | K24: Thực hành | L24: Tích hợp ở hệ thống quản lý | M24: Cho thấy structured công bố vượt khỏi marketing trang; từng metric vẫn cần classify riêng. | N24: https://silksenseresort.com/wp-content/uploads/2026/03/Travelife-V4.pdf
A25: Silk Sense Hoi An River Resort | B25: Cấp khu nghỉ dưỡng | C25: 2026–2028 | D25: Travelife Gold – doanh nghiệp công bố | E25: Silk Sense công bố được tái chứng nhận Travelife Gold cho giai đoạn 2026–2028. Research hiện tại chưa tìm thấy primary công khai Travelife directory trang để independently xác minh record. | F25: Cốt lõi | I25: C – Doanh nghiệp công bố định tính | J25: Silk Sense Sustainability | K25: Xác minh | L25: Tích hợp ở hệ thống quản lý | M25: Giữ như doanh nghiệp tự công bố chứng nhận công bố tới khi có third-party source trực tiếp. | N25: https://silksenseresort.com/sustainability/
A26: Silk Sense Hoi An River Resort | B26: Cấp khu nghỉ dưỡng | C26: 2026 | D26: Kế hoạch Hành động Phát triển Bền vững 2026 | E26: Sustainability trang công khai link Action Plan 2026 với các commitment/action areas cho vận hành bền vững. | F26: Bổ trợ | I26: C – Doanh nghiệp công bố định tính | J26: Silk Sense Sustainability | K26: Cam kết | L26: Tích hợp ở hệ thống quản lý | M26: Minh chứng về quản lý, chưa phải kết quả. | N26: https://silksenseresort.com/sustainability/
A27: Legacy Mekong | B27: Cấp khu nghỉ dưỡng | C27: Rà soát hiện tại | D27: Báo cáo/chứng nhận phát triển bền vững công khai hiện tại | E27: Trong các nguồn chính thức hiện tại đã rà, chưa tìm thấy dedicated báo cáo phát triển bền vững hoặc third-party hotel phát triển bền vững chứng nhận cho Legacy Mekong. | F27: Cốt lõi | I27: E – Chưa tìm thấy minh chứng cụ thể | J27: Rà soát các nguồn chính thức hiện tại | K27: Khoảng trống dữ liệu | L27: Tích hợp ở hệ thống quản lý | M27: Legacy Mekong có một số công bố phát triển bền vững mang tính lịch sử; mức độ minh bạch hiện tại thấp hơn các trường hợp có báo cáo/chứng nhận riêng. | N27: https://azerai.com/azerai-can-tho/accommodations/
A28: Legacy Mekong | B28: Tính liên tục của cơ sở / tên hiện tại | C28: 2024–2026 | D28: Đổi tên thành Legacy Mekong / lưu ý về tính liên tục của dữ liệu | E28: Nguồn du lịch Cần Thơ và báo cáo Novaland 2024 xác nhận cơ sở hiện vận hành dưới tên Legacy Mekong (trước đó là Azerai Can Tho). Do dữ liệu phát triển bền vững hiện tại còn ít, các thông tin lịch sử từ Azerai/Novaland được giữ với mốc thời gian rõ ràng. | F28: Cốt lõi | I28: D – Xác nhận từ nguồn công khai bên ngoài | J28: Can Tho Tourism / Novaland Annual Report 2024 | K28: Thực hành | L28: Tích hợp ở hệ thống quản lý | M28: Lưu ý phương pháp: không dùng các thông tin lịch sử của Azerai như hiệu suất hiện tại của Legacy Mekong nếu chưa có dữ liệu cập nhật. | N28: https://tourismcantho.vn/resort-azerai-can-tho/
A29: Legacy Mekong | B29: Bối cảnh chủ sở hữu trong quá khứ | C29: 2018–2020 | D29: Thông tin về phát triển/vận hành theo hướng bền vững | E29: Government/owner materials giai đoạn launch/early operation mô tả development theo hướng green spaces, energy efficiency và một số solar applications. | F29: Bổ trợ | I29: C – Doanh nghiệp công bố định tính | J29: Nguồn công khai trước đây của cơ quan nhà nước/chủ sở hữu | K29: Thực hành | L29: Tích hợp liên phòng ban | M29: lịch sử phạm vi; không dùng như hiện tại 2026 xác minh. | N29: https://baochinhphu.vn/novaland-ra-mat-resort-azerai-can-tho-102239790.htm
A30: Legacy Mekong | B30: Cấp khu nghỉ dưỡng | C30: Từ 12/2025 | D30: Khung Serve 360 của Marriott | E30: Legacy Mekong gia nhập Autograph Collection của Marriott từ tháng 12/2025. Serve 360 là khung phát triển bền vững và tác động xã hội ở cấp tập đoàn Marriott, bao gồm vận hành có trách nhiệm, quản lý năng lượng và nước, giảm chất thải/phát thải và thu mua có trách nhiệm. | F30: Bổ trợ | I30: C – Doanh nghiệp công bố định tính | J30: Trang Serve 360 chính thức của Marriott | K30: Thực hành | L30: Khung quản lý | M30: Chỉ dùng như bối cảnh quản lý ở cấp tập đoàn | N30: https://serve360.marriott.com/
A31: Legacy Mekong | B31: Property | C31: Since Dec 2025 | D31: Marriott Serve 360 framework | E31: Legacy Mekong gia nhập Autograph Collection của Marriott từ tháng 12/2025. Serve 360 là khung phát triển bền vững và tác động xã hội ở cấp tập đoàn Marriott, bao gồm vận hành có trách nhiệm, quản lý năng lượng và nước, giảm chất thải/phát thải và thu mua có trách nhiệm. | F31: Supporting | I31: C – Qualitative company-reported | J31: Marriott / Serve 360 official | K31: Practice | L31: Management framework | M31: Chỉ dùng như bối cảnh quản lý ở cấp tập đoàn | N31: https://serve360.marriott.com/

Sheet Nguồn
A1: Danh mục nguồn - toàn bộ URLs đang được dataset sử dụng
A2: Nguồn / nhãn | B2: Khu nghỉ dưỡng | C2: Khía cạnh / phạm vi | D2: Loại minh chứng | E2: Số mục sử dụng | F2: Nhóm nguồn | G2: Liên kết
A3: Trang đa dạng sinh học của Avana Retreat | B3: Avana Retreat | C3: Cộng đồng & Con người | D3: B – Doanh nghiệp công bố định lượng | E3: 1 | F3: Nguồn chính thức của doanh nghiệp / khu nghỉ dưỡng | G3: https://avanaretreat.com/biodiversity
A4: Guardians of Earth – Biocultural Health Report 2025 | B4: Avana Retreat | C4: Đa dạng sinh học & Hệ sinh thái; Quản lý & Tích hợp | D4: D – Đánh giá/xác nhận từ đối tác bên ngoài; D – Xác nhận từ đối tác bên ngoài | E4: 3 | F4: Nguồn chính thức của doanh nghiệp / khu nghỉ dưỡng | G4: https://avanaretreat.com/storage/2025/09/Biocultural-Health-Report-Avana-Retreat-2025.pdf
A5: Avana Retreat Sustainability; Rà soát các nguồn đã liệt kê | B5: Avana Retreat | C5: Đa dạng sinh học & Hệ sinh thái; Cộng đồng & Con người; Văn hóa & Di sản; Năng lượng & Khí hậu; Thực phẩm & Thu mua; Quản lý & Tích hợp; Chất thải & Nhựa; Nước | D5: B – Doanh nghiệp công bố định lượng; C – Doanh nghiệp công bố định tính; E – Chưa tìm thấy minh chứng cụ thể | E5: 9 | F5: Nguồn chính thức của doanh nghiệp / khu nghỉ dưỡng | G5: https://avanaretreat.com/sustainability
A6: Các trang phát triển bền vững của Avana Retreat | B6: Avana Retreat | C6: Gắn kết khách hàng | D6: C – Doanh nghiệp công bố định tính | E6: 1 | F6: Nguồn chính thức của doanh nghiệp / khu nghỉ dưỡng | G6: https://avanaretreat.com/sustainability/organic-life.html
A7: Azerai Can Tho official / government launch; Azerai accommodation pages; Rà soát các nguồn chính thức hiện tại; Rà soát các nguồn đã liệt kê | B7: Azerai Can Tho | C7: Cộng đồng & Con người; Văn hóa & Di sản; Thực phẩm & Thu mua; Gắn kết khách hàng; Quản lý & Tích hợp; Chất thải & Nhựa; Nước | D7: C – Doanh nghiệp công bố định tính; E – Chưa tìm thấy minh chứng cụ thể | E7: 7 | F7: Nguồn chính thức của doanh nghiệp / khu nghỉ dưỡng | G7: https://azerai.com/azerai-can-tho/accommodations/
A8: Nguồn công khai trước đây của cơ quan nhà nước/chủ sở hữu | B8: Azerai Can Tho | C8: Quản lý & Tích hợp | D8: C – Doanh nghiệp công bố định tính | E8: 1 | F8: Nguồn bên ngoài / độc lập / công khai | G8: https://baochinhphu.vn/novaland-ra-mat-resort-azerai-can-tho-102239790.htm
A9: Can Tho Tourism / Novaland Annual Report 2024; Trang điểm đến của cơ quan du lịch Cần Thơ | B9: Azerai Can Tho | C9: Đa dạng sinh học & Hệ sinh thái; Quản lý & Tích hợp | D9: D – Xác nhận từ nguồn công khai bên ngoài; D – Xác nhận từ nguồn du lịch công khai bên ngoài | E9: 2 | F9: Nguồn bên ngoài / độc lập / công khai | G9: https://tourismcantho.vn/resort-azerai-can-tho/
A10: Novaland Sustainability Report 2018 | B10: Azerai Can Tho | C10: Năng lượng & Khí hậu | D10: B – Doanh nghiệp công bố định lượng | E10: 1 | F10: Nguồn chính thức của doanh nghiệp / khu nghỉ dưỡng | G10: https://www.novaland.com.vn/Data/Sites/1/media/phat-trien-ben-vung/bao-cao-ptbv/nvl_sr2018_en_0606_final.pdf
A11: Thông tin chính thức trước đây của chủ sở hữu | B11: Azerai Can Tho | C11: Năng lượng & Khí hậu | D11: B – Doanh nghiệp công bố định lượng | E11: 1 | F11: Nguồn chính thức của doanh nghiệp / khu nghỉ dưỡng | G11: https://www.novaland.com.vn/ung-dung-he-thong-xe-dien-buggy-chay-bang-nang-luong-mat-troi-tai-azerai-can-tho-resort
A12: EarthCheck | B12: Banyan Tree Lang Co | C12: Quản lý & Tích hợp | D12: A – Xác minh độc lập | E12: 1 | F12: Nguồn bên ngoài / độc lập / công khai | G12: https://earthcheck.org/news/laguna-golf-lang-co-retains-earthcheck-gold/
A13: Trang đa dạng sinh học của Banyan Tree Lang Co | B13: Banyan Tree Lang Co | C13: Đa dạng sinh học & Hệ sinh thái | D13: B – Doanh nghiệp công bố định lượng | E13: 1 | F13: Nguồn chính thức của doanh nghiệp / khu nghỉ dưỡng | G13: https://www.banyantree.com/vietnam/lang-co/biodiversity-at-banyan-tree-lang-co
A14: Banyan Tree Lang Co Stay for Good | B14: Banyan Tree Lang Co | C14: Đa dạng sinh học & Hệ sinh thái; Văn hóa & Di sản; Gắn kết khách hàng | D14: C – Doanh nghiệp công bố định tính | E14: 3 | F14: Nguồn chính thức của doanh nghiệp / khu nghỉ dưỡng | G14: https://www.banyantree.com/vietnam/lang-co/experiences/stay-for-good
... A48: Topas Ecolodge – ASEAN Green Hotel 2026 page; Topas Sustainable Development + ASEAN Green Hotel 2026 disclosure; Topas Sustainable Development + ASEAN Green Hotel 2026 page | B48: Topas Ecolodge | C48: Cộng đồng & Con người; Năng lượng & Khí hậu; Thực phẩm & Thu mua; Gắn kết khách hàng; Chất thải & Nhựa; Nước | D48: B – Doanh nghiệp công bố định lượng; C – Doanh nghiệp công bố định tính | E48: 6 | F48: Nguồn chính thức của doanh nghiệp / khu nghỉ dưỡng | G48: https://topasecolodge.com/topas-ecolodge-recognized-as-asean-green-hotel-2026/
